[{"c":"A66078902","s":"가좌3주공-a66078902","q":1,"n":"가좌3주공","sd":"경상남도","sg":"진주시","d":"가좌동","a":"경상남도 진주시 진주대로568번길 12","h":758,"b":9,"y":2005,"ht":"개별난방","mt":"위탁관리","ma":47348,"lm":"2026-05","tf":1672,"cf":1184,"rf":0,"la":35.1569387,"lo":128.1098909},{"c":"A66077903","s":"가좌그린빌주공-a66077903","q":1,"n":"가좌그린빌주공","sd":"경상남도","sg":"진주시","d":"가좌동","a":"경상남도 진주시 내동로348번길 10","h":1372,"b":16,"y":2005,"ht":"개별난방","mt":"위탁관리","ma":124699,"lm":"2026-05","tf":1645,"cf":882,"rf":200,"la":35.1485791,"lo":128.101328},{"c":"A10021300","s":"가좌대화리네르빌-a10021300","q":0,"n":"가좌대화리네르빌","sd":"경상남도","sg":"진주시","d":"가좌동","a":"경상남도 진주시 가좌동 721-1 가좌대화리네르빌","h":137,"b":3,"y":2007,"ht":"개별난방","mt":"자치관리","ma":14674,"lm":"2026-04","tf":1475,"cf":556,"rf":187,"la":35.1649637,"lo":128.106937},{"c":"A66070102","s":"가좌올리움-a66070102","q":1,"n":"가좌올리움","sd":"경상남도","sg":"진주시","d":"가좌동","a":"경상남도 진주시 가호로 17-10","h":442,"b":4,"y":2012,"ht":"개별난방","mt":"위탁관리","ma":40674,"lm":"2026-05","tf":1502,"cf":1043,"rf":0,"la":35.1646124,"lo":128.1082756},{"c":"A66070101","s":"가호에일린의뜰-a66070101","q":1,"n":"가호에일린의뜰","sd":"경상남도","sg":"진주시","d":"가좌동","a":"경상남도 진주시 강변길 31","h":369,"b":5,"y":2012,"ht":"개별난방","mt":"위탁관리","ma":43896,"lm":"2026-05","tf":1860,"cf":1062,"rf":137,"la":35.1654058,"lo":128.1091129},{"c":"A10026639","s":"건영-아모리움-a10026639","q":1,"n":"건영 아모리움","sd":"경상남도","sg":"진주시","d":"평거동","a":"경상남도 진주시 진양호로225번길 13","h":236,"b":2,"y":2017,"ht":"개별난방","mt":"위탁관리","ma":24492,"lm":"2026-05","tf":1986,"cf":1079,"rf":140,"la":35.1745755,"lo":128.059628},{"c":"A10021641","s":"건일아파트-a10021641","q":1,"n":"건일아파트","sd":"경상남도","sg":"진주시","d":"하대동","a":"경상남도 진주시 하대동 134-2 건일아파트","h":120,"b":1,"y":1987,"ht":"개별난방","mt":"자치관리","ma":7189,"lm":"2026-05","tf":1041,"cf":527,"rf":250,"la":35.1864723,"lo":128.1255044},{"c":"A10026929","s":"경남혁신도시lh9단지-a10026929","q":1,"n":"경남혁신도시LH9단지","sd":"경상남도","sg":"진주시","d":"충무공동","a":"경상남도 진주시 사들로 13","h":630,"b":6,"y":2017,"ht":"지역난방","mt":"위탁관리","ma":51941,"lm":"2026-05","tf":2247,"cf":1133,"rf":143,"la":35.1712567,"lo":128.145124},{"c":"A10021358","s":"경상국립대-행복주택-a10021358","q":0,"n":"경상국립대 행복주택","sd":"경상남도","sg":"진주시","d":"가좌동","a":"경상남도 진주시 가좌동 843 경상국립대 행복주택","h":150,"b":1,"y":2024,"ht":"개별난방","mt":"위탁관리","ma":0,"lm":"","tf":0,"cf":0,"rf":0,"la":35.1579648,"lo":128.1003491},{"c":"A10021671","s":"국민주택아파트-a10021671","q":1,"n":"국민주택아파트","sd":"경상남도","sg":"진주시","d":"평거동","a":"경상남도 진주시 평거동 741-1 국민주택아파트","h":100,"b":1,"y":1992,"ht":"개별난방","mt":"위탁관리","ma":4771,"lm":"2026-05","tf":1518,"cf":803,"rf":419,"la":35.1688989,"lo":128.050614},{"c":"A10022191","s":"국제아파트-a10022191","q":0,"n":"국제아파트","sd":"경상남도","sg":"진주시","d":"신안동","a":"경상남도 진주시 신안동 408-1,경상남도 진주시 신안동 409-2 국제아파트","h":151,"b":4,"y":1987,"ht":"개별난방","mt":"관리방식미정","ma":8615,"lm":"2026-04","tf":1083,"cf":837,"rf":0,"la":35.1819415,"lo":128.0634396},{"c":"A10021653","s":"그린타운-a10021653","q":1,"n":"그린타운","sd":"경상남도","sg":"진주시","d":"신안동","a":"경상남도 진주시 신안동 412- 그린타운","h":112,"b":1,"y":1992,"ht":"개별난방","mt":"위탁관리","ma":11010,"lm":"2026-05","tf":1103,"cf":461,"rf":389,"la":35.1829702,"lo":128.0643557},{"c":"A66093101","s":"금빛마을현대아파트-a66093101","q":1,"n":"금빛마을현대아파트","sd":"경상남도","sg":"진주시","d":"봉강리","a":"경상남도 진주시 진산로 675","h":667,"b":9,"y":2000,"ht":"개별난방","mt":"위탁관리","ma":62865,"lm":"2026-05","tf":1637,"cf":790,"rf":296,"la":35.2385953,"lo":128.0890434},{"c":"A66092106","s":"금산두산위브-a66092106","q":1,"n":"금산두산위브","sd":"경상남도","sg":"진주시","d":"장사리","a":"경상남도 진주시 중장로154번길 49","h":970,"b":13,"y":2009,"ht":"개별난방","mt":"위탁관리","ma":122052,"lm":"2026-05","tf":1640,"cf":813,"rf":149,"la":35.2202982,"lo":128.1490387},{"c":"A66092108","s":"금산아이파크-a66092108","q":1,"n":"금산아이파크","sd":"경상남도","sg":"진주시","d":"장사리","a":"경상남도 진주시 중천로 82","h":735,"b":11,"y":2004,"ht":"개별난방","mt":"위탁관리","ma":85212,"lm":"2026-05","tf":1713,"cf":825,"rf":246,"la":35.2164545,"lo":128.1455145},{"c":"A66092109","s":"금산진흥더루벤스-a66092109","q":1,"n":"금산진흥더루벤스","sd":"경상남도","sg":"진주시","d":"중천리","a":"경상남도 진주시 금산로 22","h":404,"b":7,"y":2009,"ht":"개별난방","mt":"위탁관리","ma":42083,"lm":"2026-05","tf":2396,"cf":1060,"rf":495,"la":35.2133271,"lo":128.1404204},{"c":"A66092107","s":"금산흥한골든빌-a66092107","q":1,"n":"금산흥한골든빌","sd":"경상남도","sg":"진주시","d":"장사리","a":"경상남도 진주시 금산로 123","h":1709,"b":18,"y":2002,"ht":"개별난방","mt":"자치관리","ma":147619,"lm":"2026-05","tf":1354,"cf":615,"rf":200,"la":35.2147682,"lo":128.1504474},{"c":"A66092102","s":"금산e편한세상-a66092102","q":1,"n":"금산e편한세상","sd":"경상남도","sg":"진주시","d":"장사리","a":"경상남도 진주시 금산순환로80번길 16","h":400,"b":4,"y":2008,"ht":"개별난방","mt":"위탁관리","ma":57247,"lm":"2026-05","tf":1559,"cf":740,"rf":250,"la":35.2202152,"lo":128.1528864},{"c":"A66029003","s":"금호석류마을-a66029003","q":1,"n":"금호석류마을","sd":"경상남도","sg":"진주시","d":"주약동","a":"경상남도 진주시 강남로 45","h":782,"b":15,"y":1999,"ht":"개별난방","mt":"위탁관리","ma":69904,"lm":"2026-05","tf":1852,"cf":976,"rf":199,"la":35.172675,"lo":128.0951709},{"c":"A66081101","s":"남강휴먼빌-a66081101","q":1,"n":"남강휴먼빌","sd":"경상남도","sg":"진주시","d":"독산리","a":"경상남도 진주시 순환로 425-61","h":916,"b":11,"y":2010,"ht":"개별난방","mt":"위탁관리","ma":125687,"lm":"2026-05","tf":1499,"cf":716,"rf":182,"la":35.1625108,"lo":128.0658587},{"c":"A66079203","s":"느티나무-a66079203","q":1,"n":"느티나무","sd":"경상남도","sg":"진주시","d":"장사리","a":"경상남도 진주시 중천로 74","h":450,"b":6,"y":2003,"ht":"개별난방","mt":"위탁관리","ma":41831,"lm":"2026-05","tf":2024,"cf":1084,"rf":280,"la":35.2177063,"lo":128.1446901},{"c":"A66025001","s":"대경강남타운-a66025001","q":0,"n":"대경강남타운","sd":"경상남도","sg":"진주시","d":"강남동","a":"경상남도 진주시 진주대로891번길 16","h":179,"b":1,"y":1997,"ht":"개별난방","mt":"위탁관리","ma":13144,"lm":"2026-04","tf":1597,"cf":810,"rf":154,"la":35.1803113,"lo":128.0896977},{"c":"A10021592","s":"대경그린파크-a10021592","q":0,"n":"대경그린파크","sd":"경상남도","sg":"진주시","d":"평거동","a":"경상남도 진주시 평거동 136-6 대경그린파크","h":121,"b":1,"y":1994,"ht":"개별난방","mt":"자치관리","ma":10476,"lm":"2026-04","tf":1405,"cf":1032,"rf":120,"la":35.1731342,"lo":128.0577905},{"c":"A10022010","s":"대경아르떼빌-a10022010","q":1,"n":"대경아르떼빌","sd":"경상남도","sg":"진주시","d":"호탄동","a":"경상남도 진주시 호탄동 620-1 대경아르떼빌","h":131,"b":1,"y":2002,"ht":"개별난방","mt":"자치관리","ma":6391,"lm":"2026-05","tf":2079,"cf":1336,"rf":188,"la":35.1620122,"lo":128.1144939},{"c":"A10021541","s":"대동아파트-a10021541","q":0,"n":"대동아파트","sd":"경상남도","sg":"진주시","d":"상대동","a":"경상남도 진주시 상대동 331-1 대동아파트","h":160,"b":5,"y":1979,"ht":"개별난방","mt":"자치관리","ma":10215,"lm":"2026-04","tf":864,"cf":603,"rf":94,"la":35.186063,"lo":128.1192165},{"c":"A66078803","s":"대동황토방-a66078803","q":1,"n":"대동황토방","sd":"경상남도","sg":"진주시","d":"호탄동","a":"경상남도 진주시 가호로44번길 7","h":496,"b":7,"y":2003,"ht":"개별난방","mt":"위탁관리","ma":50381,"lm":"2026-05","tf":1711,"cf":883,"rf":220,"la":35.162575,"lo":128.1121503},{"c":"A66098602","s":"대림-a66098602","q":1,"n":"대림","sd":"경상남도","sg":"진주시","d":"초전동","a":"경상남도 진주시 말티고개로 113","h":305,"b":3,"y":1995,"ht":"개별난방","mt":"위탁관리","ma":28820,"lm":"2026-05","tf":1516,"cf":729,"rf":242,"la":35.197364,"lo":128.1138567},{"c":"A10028091","s":"더-퀸즈-웰가-a10028091","q":1,"n":"더 퀸즈 웰가","sd":"경상남도","sg":"진주시","d":"평거동","a":"경상남도 진주시 새평거로 25","h":1308,"b":12,"y":2015,"ht":"개별난방","mt":"위탁관리","ma":132364,"lm":"2026-05","tf":2640,"cf":962,"rf":135,"la":35.1666041,"lo":128.0517279},{"c":"A10020937","s":"더샵-진주피에르테-a10020937","q":1,"n":"더샵 진주피에르테","sd":"경상남도","sg":"진주시","d":"초전동","a":"경상남도 진주시 초전동 1752- 더샵 진주피에르테","h":798,"b":7,"y":2024,"ht":"개별난방","mt":"위탁관리","ma":91735,"lm":"2026-05","tf":1842,"cf":832,"rf":110,"la":35.211957,"lo":128.1070443},{"c":"A66033006","s":"도동대림아파트-a66033006","q":1,"n":"도동대림아파트","sd":"경상남도","sg":"진주시","d":"하대동","a":"경상남도 진주시 하대로40번길 4","h":283,"b":2,"y":1992,"ht":"개별난방","mt":"위탁관리","ma":28851,"lm":"2026-05","tf":1235,"cf":747,"rf":248,"la":35.1923846,"lo":128.1151605},{"c":"A10021700","s":"도운아파트-a10021700","q":0,"n":"도운아파트","sd":"경상남도","sg":"진주시","d":"하대동","a":"경상남도 진주시 하대동 111- 도운아파트","h":115,"b":2,"y":1986,"ht":"","mt":"자치관리","ma":7012,"lm":"2026-04","tf":830,"cf":385,"rf":235,"la":35.1885679,"lo":128.1282054},{"c":"A10021877","s":"동국1차강변타워-a10021877","q":0,"n":"동국1차강변타워","sd":"경상남도","sg":"진주시","d":"상평동","a":"경상남도 진주시 상평동 227- 동국1차강변타워","h":126,"b":1,"y":1991,"ht":"개별난방","mt":"위탁관리","ma":11980,"lm":"2026-04","tf":1454,"cf":975,"rf":181,"la":35.1700718,"lo":128.1095404},{"c":"A66090202","s":"동국제2강변타워-a66090202","q":1,"n":"동국제2강변타워","sd":"경상남도","sg":"진주시","d":"상평동","a":"경상남도 진주시 돗골로19번길 10","h":162,"b":1,"y":1992,"ht":"개별난방","mt":"위탁관리","ma":15470,"lm":"2026-05","tf":1473,"cf":1083,"rf":242,"la":35.1701291,"lo":128.1120315},{"c":"A66080801","s":"동서훼미리-a66080801","q":1,"n":"동서훼미리","sd":"경상남도","sg":"진주시","d":"상대동","a":"경상남도 진주시 선학산길 22","h":162,"b":2,"y":1992,"ht":"개별난방","mt":"위탁관리","ma":9054,"lm":"2026-05","tf":2186,"cf":1509,"rf":346,"la":35.1841155,"lo":128.1091679},{"c":"A66025002","s":"동성가든타워-a66025002","q":1,"n":"동성가든타워","sd":"경상남도","sg":"진주시","d":"강남동","a":"경상남도 진주시 진주대로 901","h":195,"b":3,"y":1994,"ht":"개별난방","mt":"자치관리","ma":19539,"lm":"2026-05","tf":1486,"cf":824,"rf":120,"la":35.1809492,"lo":128.0893496},{"c":"A66077407","s":"들말대경-a66077407","q":1,"n":"들말대경","sd":"경상남도","sg":"진주시","d":"평거동","a":"경상남도 진주시 석갑로53번길 10","h":750,"b":10,"y":1998,"ht":"개별난방","mt":"위탁관리","ma":74315,"lm":"2026-05","tf":1880,"cf":1018,"rf":270,"la":35.176185,"lo":128.063422},{"c":"A66077508","s":"들말한보타운-a66077508","q":1,"n":"들말한보타운","sd":"경상남도","sg":"진주시","d":"평거동","a":"경상남도 진주시 평거로39번길 9","h":791,"b":8,"y":1997,"ht":"중앙난방","mt":"위탁관리","ma":63907,"lm":"2026-05","tf":2652,"cf":1199,"rf":422,"la":35.1734772,"lo":128.0633782},{"c":"A66077609","s":"들말흥한타운-a66077609","q":1,"n":"들말흥한타운","sd":"경상남도","sg":"진주시","d":"평거동","a":"경상남도 진주시 석갑로 45","h":960,"b":13,"y":1998,"ht":"개별난방","mt":"위탁관리","ma":97364,"lm":"2026-05","tf":1571,"cf":757,"rf":160,"la":35.1754165,"lo":128.0648703},{"c":"A66099501","s":"럭키강변타워-a66099501","q":1,"n":"럭키강변타워","sd":"경상남도","sg":"진주시","d":"하대동","a":"경상남도 진주시 남강로 1407","h":150,"b":1,"y":1991,"ht":"개별난방","mt":"위탁관리","ma":13884,"lm":"2026-05","tf":1574,"cf":820,"rf":184,"la":35.1865836,"lo":128.1282158},{"c":"A66026001","s":"망경한보타운-a66026001","q":1,"n":"망경한보타운","sd":"경상남도","sg":"진주시","d":"망경동","a":"경상남도 진주시 망경로 234-5","h":886,"b":6,"y":1997,"ht":"개별난방","mt":"위탁관리","ma":85209,"lm":"2026-05","tf":1579,"cf":668,"rf":320,"la":35.1821768,"lo":128.0802203},{"c":"A66095301","s":"명석동신-a66095301","q":1,"n":"명석동신","sd":"경상남도","sg":"진주시","d":"우수리","a":"경상남도 진주시 광제산로 11-21","h":490,"b":4,"y":1992,"ht":"개별난방","mt":"위탁관리","ma":42654,"lm":"2026-05","tf":1680,"cf":742,"rf":291,"la":35.2171284,"lo":128.0390083},{"c":"A66099104","s":"벽산동신-a66099104","q":1,"n":"벽산동신","sd":"경상남도","sg":"진주시","d":"평거동","a":"경상남도 진주시 진양호로125번길 22-12","h":286,"b":3,"y":1993,"ht":"개별난방","mt":"자치관리","ma":29496,"lm":"2026-05","tf":1207,"cf":730,"rf":272,"la":35.1709109,"lo":128.0526547},{"c":"A10021548","s":"삼전1차맨션-a10021548","q":0,"n":"삼전1차맨션","sd":"경상남도","sg":"진주시","d":"하대동","a":"경상남도 진주시 하대동 102-2 삼전1차맨션","h":100,"b":3,"y":1988,"ht":"개별난방","mt":"자치관리","ma":7699,"lm":"2026-04","tf":1065,"cf":498,"rf":325,"la":35.1916883,"lo":128.1277098},{"c":"A66033003","s":"삼전프라자-a66033003","q":0,"n":"삼전프라자","sd":"경상남도","sg":"진주시","d":"하대동","a":"경상남도 진주시 도동로 251","h":176,"b":2,"y":1996,"ht":"개별난방","mt":"위탁관리","ma":16144,"lm":"2026-04","tf":1882,"cf":967,"rf":303,"la":35.1927722,"lo":128.1211931},{"c":"A66077001","s":"삼환나우빌-a66077001","q":1,"n":"삼환나우빌","sd":"경상남도","sg":"진주시","d":"주약동","a":"경상남도 진주시 진주대로829번길 21","h":220,"b":3,"y":2009,"ht":"개별난방","mt":"위탁관리","ma":37207,"lm":"2026-05","tf":1910,"cf":940,"rf":300,"la":35.1739474,"lo":128.0916069},{"c":"A66033009","s":"상대주공-a66033009","q":1,"n":"상대주공","sd":"경상남도","sg":"진주시","d":"하대동","a":"경상남도 진주시 상대로 101","h":510,"b":11,"y":1980,"ht":"개별난방","mt":"위탁관리","ma":21917,"lm":"2026-05","tf":941,"cf":838,"rf":92,"la":35.1851553,"lo":128.1237418},{"c":"A66076402","s":"상대한보타운-a66076402","q":1,"n":"상대한보타운","sd":"경상남도","sg":"진주시","d":"상대동","a":"경상남도 진주시 도동천로 120","h":805,"b":6,"y":2002,"ht":"개별난방","mt":"위탁관리","ma":86700,"lm":"2026-05","tf":1518,"cf":650,"rf":300,"la":35.1812074,"lo":128.1135661},{"c":"A66032001","s":"상대한주그린-a66032001","q":1,"n":"상대한주그린","sd":"경상남도","sg":"진주시","d":"상대동","a":"경상남도 진주시 선학산길 48","h":110,"b":1,"y":1999,"ht":"개별난방","mt":"위탁관리","ma":9883,"lm":"2026-05","tf":2107,"cf":982,"rf":423,"la":35.1862215,"lo":128.1108296},{"c":"A66076302","s":"상대현대-a66076302","q":1,"n":"상대현대","sd":"경상남도","sg":"진주시","d":"상대동","a":"경상남도 진주시 모덕로181번길 7","h":684,"b":9,"y":1991,"ht":"개별난방","mt":"위탁관리","ma":58711,"lm":"2026-05","tf":2166,"cf":1060,"rf":374,"la":35.1872,"lo":128.113159},{"c":"A10021514","s":"상대흥한아파트-a10021514","q":0,"n":"상대흥한아파트","sd":"경상남도","sg":"진주시","d":"상대동","a":"경상남도 진주시 상대동 307-4 상대흥한아파트","h":108,"b":1,"y":1995,"ht":"개별난방","mt":"자치관리","ma":9316,"lm":"2026-04","tf":1237,"cf":625,"rf":348,"la":35.1824179,"lo":128.1162975},{"c":"A66076501","s":"상봉1차-a66076501","q":1,"n":"상봉1차","sd":"경상남도","sg":"진주시","d":"상봉동","a":"경상남도 진주시 창렬로 129,경상남도 진주시 창렬로 123","h":650,"b":13,"y":1976,"ht":"개별난방","mt":"위탁관리","ma":26728,"lm":"2026-05","tf":1035,"cf":820,"rf":40,"la":35.1987408,"lo":128.0698735},{"c":"A10021129","s":"상봉2차주공아파트-a10021129","q":1,"n":"상봉2차주공아파트","sd":"경상남도","sg":"진주시","d":"상봉동","a":"경상남도 진주시 상봉동 1446- 상봉2차주공아파트","h":260,"b":9,"y":1986,"ht":"개별난방","mt":"자치관리","ma":15732,"lm":"2026-05","tf":1172,"cf":691,"rf":254,"la":35.2032662,"lo":128.0733098},{"c":"A66005002","s":"상봉한주타운-a66005002","q":1,"n":"상봉한주타운","sd":"경상남도","sg":"진주시","d":"상봉동","a":"경상남도 진주시 진주대로1208번길 20","h":467,"b":5,"y":1992,"ht":"개별난방","mt":"자치관리(직영)","ma":56159,"lm":"2026-05","tf":1301,"cf":591,"rf":200,"la":35.1959501,"lo":128.0711809},{"c":"A66005001","s":"상봉화인-a66005001","q":1,"n":"상봉화인","sd":"경상남도","sg":"진주시","d":"상봉동","a":"경상남도 진주시 상봉대룡길 18","h":459,"b":4,"y":1994,"ht":"개별난방","mt":"위탁관리","ma":45462,"lm":"2026-05","tf":1647,"cf":781,"rf":270,"la":35.201611,"lo":128.0684055},{"c":"A66090401","s":"상평대림-a66090401","q":0,"n":"상평대림","sd":"경상남도","sg":"진주시","d":"상평동","a":"경상남도 진주시 남강로 951","h":158,"b":3,"y":1989,"ht":"개별난방","mt":"자치관리","ma":17886,"lm":"2026-04","tf":1810,"cf":830,"rf":419,"la":35.1742991,"lo":128.1001569},{"c":"A10021886","s":"상평동신아파트-a10021886","q":0,"n":"상평동신아파트","sd":"경상남도","sg":"진주시","d":"상평동","a":"경상남도 진주시 상평동 218-4 상평동신아파트","h":107,"b":1,"y":1997,"ht":"개별난방","mt":"자치관리","ma":8121,"lm":"2026-04","tf":1417,"cf":686,"rf":132,"la":35.1783311,"lo":128.1106767},{"c":"A66034003","s":"상평동일스위트-a66034003","q":1,"n":"상평동일스위트","sd":"경상남도","sg":"진주시","d":"상평동","a":"경상남도 진주시 공단로 30","h":652,"b":11,"y":2008,"ht":"개별난방","mt":"위탁관리","ma":74316,"lm":"2026-05","tf":1760,"cf":765,"rf":258,"la":35.1738841,"lo":128.1029802},{"c":"A10021885","s":"석류아파트-a10021885","q":0,"n":"석류아파트","sd":"경상남도","sg":"진주시","d":"상평동","a":"경상남도 진주시 상평동 276-4 석류아파트","h":100,"b":2,"y":1987,"ht":"개별난방","mt":"자치관리","ma":6096,"lm":"2026-04","tf":604,"cf":312,"rf":82,"la":35.1741632,"lo":128.1040792},{"c":"A10025903","s":"센트럴웰가아파트-a10025903","q":1,"n":"센트럴웰가아파트","sd":"경상남도","sg":"진주시","d":"가좌동","a":"경상남도 진주시 진주역로73번길 33","h":1152,"b":10,"y":2018,"ht":"개별난방","mt":"위탁관리","ma":126361,"lm":"2026-05","tf":1804,"cf":831,"rf":180,"la":35.1538668,"lo":128.1115994},{"c":"A10022203","s":"신안-한보타워맨션-a10022203","q":0,"n":"신안 한보타워맨션","sd":"경상남도","sg":"진주시","d":"신안동","a":"경상남도 진주시 신안동 28-4 신안 한보타워맨션","h":132,"b":1,"y":1991,"ht":"개별난방","mt":"위탁관리","ma":13448,"lm":"2026-03","tf":1287,"cf":905,"rf":181,"la":35.182624,"lo":128.0725129},{"c":"A66090809","s":"신안1차주공-a66090809","q":1,"n":"신안1차주공","sd":"경상남도","sg":"진주시","d":"신안동","a":"경상남도 진주시 신안들말길 17","h":787,"b":13,"y":1998,"ht":"개별난방","mt":"위탁관리","ma":101288,"lm":"2026-05","tf":1429,"cf":715,"rf":203,"la":35.1774809,"lo":128.0690474},{"c":"A66090803","s":"신안2차흥한타운-a66090803","q":1,"n":"신안2차흥한타운","sd":"경상남도","sg":"진주시","d":"신안동","a":"경상남도 진주시 평거로139번길 11-3","h":345,"b":3,"y":1995,"ht":"개별난방","mt":"위탁관리","ma":27710,"lm":"2026-05","tf":1815,"cf":1006,"rf":516,"la":35.1809839,"lo":128.0684291},{"c":"A66090810","s":"신안3주공-a66090810","q":1,"n":"신안3주공","sd":"경상남도","sg":"진주시","d":"신안동","a":"경상남도 진주시 석갑로 58","h":1046,"b":14,"y":1997,"ht":"개별난방","mt":"위탁관리","ma":87533,"lm":"2026-05","tf":1441,"cf":783,"rf":180,"la":35.1774403,"lo":128.0656938},{"c":"A66090806","s":"신안주공2단지-a66090806","q":1,"n":"신안주공2단지","sd":"경상남도","sg":"진주시","d":"신안동","a":"경상남도 진주시 신안들말길 47","h":519,"b":5,"y":1996,"ht":"개별난방","mt":"위탁관리","ma":32653,"lm":"2026-05","tf":1862,"cf":1070,"rf":247,"la":35.1788202,"lo":128.066653},{"c":"A66090807","s":"신안주공2차21-a66090807","q":1,"n":"신안주공2차21","sd":"경상남도","sg":"진주시","d":"신안동","a":"경상남도 진주시 신안들말길 47","h":660,"b":8,"y":1996,"ht":"개별난방","mt":"위탁관리","ma":52364,"lm":"2026-05","tf":1950,"cf":934,"rf":326,"la":35.1788202,"lo":128.066653},{"c":"A66078706","s":"신안평거한보타운-a66078706","q":1,"n":"신안평거한보타운","sd":"경상남도","sg":"진주시","d":"평거동","a":"경상남도 진주시 진양호로97번길 19-6","h":485,"b":3,"y":1993,"ht":"개별난방","mt":"위탁관리","ma":47750,"lm":"2026-05","tf":1713,"cf":857,"rf":304,"la":35.1695137,"lo":128.049709},{"c":"A66090508","s":"신안현대-a66090508","q":1,"n":"신안현대","sd":"경상남도","sg":"진주시","d":"신안동","a":"경상남도 진주시 천수로 315","h":694,"b":7,"y":1989,"ht":"개별난방","mt":"위탁관리","ma":74497,"lm":"2026-05","tf":1644,"cf":961,"rf":169,"la":35.1840668,"lo":128.071807},{"c":"A10022624","s":"신진주라비에데시앙-a10022624","q":1,"n":"신진주라비에데시앙","sd":"경상남도","sg":"진주시","d":"가좌동","a":"경상남도 진주시 개양로 145","h":810,"b":11,"y":2024,"ht":"개별난방","mt":"위탁관리","ma":94431,"lm":"2026-05","tf":1782,"cf":722,"rf":92,"la":35.1533785,"lo":128.1222817},{"c":"A10024740","s":"신진주시티프라디움2차아파트-a10024740","q":1,"n":"신진주시티프라디움2차아파트","sd":"경상남도","sg":"진주시","d":"가좌동","a":"경상남도 진주시 진주역로 114","h":407,"b":3,"y":2020,"ht":"개별난방","mt":"위탁관리","ma":45951,"lm":"2026-05","tf":1756,"cf":889,"rf":113,"la":35.1512179,"lo":128.1158952},{"c":"A10022148","s":"에스디푸른마을아파트-a10022148","q":0,"n":"에스디푸른마을아파트","sd":"경상남도","sg":"진주시","d":"상봉동","a":"경상남도 진주시 상봉동 740- 에스디푸른마을아파트","h":116,"b":3,"y":2010,"ht":"개별난방","mt":"위탁관리","ma":11058,"lm":"2026-04","tf":2268,"cf":981,"rf":400,"la":35.2028115,"lo":128.0672656},{"c":"A66077411","s":"엠코타운더프라하-a66077411","q":1,"n":"엠코타운더프라하","sd":"경상남도","sg":"진주시","d":"평거동","a":"경상남도 진주시 새평거로 30","h":1813,"b":14,"y":2014,"ht":"개별난방","mt":"위탁관리","ma":226194,"lm":"2026-05","tf":1796,"cf":811,"rf":200,"la":35.1649844,"lo":128.052302},{"c":"A10025572","s":"옥봉대림아파트-a10025572","q":1,"n":"옥봉대림아파트","sd":"경상남도","sg":"진주시","d":"옥봉동","a":"경상남도 진주시 옥봉동 176-1 옥봉대림아파트","h":145,"b":1,"y":1993,"ht":"개별난방","mt":"위탁관리","ma":14914,"lm":"2026-05","tf":1607,"cf":942,"rf":242,"la":35.1959007,"lo":128.0940192},{"c":"A10022558","s":"우미린-더시그니처-a10022558","q":1,"n":"우미린 더시그니처","sd":"경상남도","sg":"진주시","d":"가좌동","a":"경상남도 진주시 진주역로 55","h":828,"b":13,"y":2024,"ht":"개별난방","mt":"위탁관리","ma":96621,"lm":"2026-05","tf":1948,"cf":832,"rf":164,"la":35.1511906,"lo":128.1092789},{"c":"A10020659","s":"우신파크맨션-a10020659","q":1,"n":"우신파크맨션","sd":"경상남도","sg":"진주시","d":"이현동","a":"경상남도 진주시 이현동 270- 우신파크맨션","h":104,"b":1,"y":1992,"ht":"개별난방","mt":"자치관리","ma":10511,"lm":"2026-05","tf":1048,"cf":732,"rf":147,"la":35.190364,"lo":128.0579253},{"c":"A10021898","s":"원정로얄팰리스-a10021898","q":0,"n":"원정로얄팰리스","sd":"경상남도","sg":"진주시","d":"평거동","a":"경상남도 진주시 평거동 146- 원정로얄팰리스","h":100,"b":2,"y":2005,"ht":"","mt":"자치관리","ma":12060,"lm":"2026-04","tf":1893,"cf":1004,"rf":149,"la":35.1747838,"lo":128.0608088},{"c":"A66007001","s":"유곡한보-a66007001","q":0,"n":"유곡한보","sd":"경상남도","sg":"진주시","d":"유곡동","a":"경상남도 진주시 진주대로 1278","h":204,"b":1,"y":1994,"ht":"개별난방","mt":"위탁관리","ma":19358,"lm":"2026-04","tf":1386,"cf":739,"rf":299,"la":35.1943361,"lo":128.0635881},{"c":"A66098301","s":"이현덕산-a66098301","q":1,"n":"이현덕산","sd":"경상남도","sg":"진주시","d":"이현동","a":"경상남도 진주시 서장대로178번길 17","h":231,"b":1,"y":1995,"ht":"개별난방","mt":"위탁관리","ma":16565,"lm":"2026-05","tf":2047,"cf":1026,"rf":232,"la":35.1875829,"lo":128.0588938},{"c":"A66008003","s":"이현하이클래스웰가-a66008003","q":1,"n":"이현하이클래스웰가","sd":"경상남도","sg":"진주시","d":"이현동","a":"경상남도 진주시 진주대로 1317","h":1268,"b":14,"y":2008,"ht":"개별난방","mt":"위탁관리","ma":164408,"lm":"2026-05","tf":1616,"cf":667,"rf":300,"la":35.1939719,"lo":128.0574169},{"c":"A10022106","s":"일진스위트포레강남-a10022106","q":0,"n":"일진스위트포레강남","sd":"경상남도","sg":"진주시","d":"강남동","a":"경상남도 진주시 강남동 141-1 일진스위트포레강남","h":115,"b":1,"y":2021,"ht":"","mt":"위탁관리","ma":8500,"lm":"2026-03","tf":3367,"cf":2088,"rf":192,"la":35.1855573,"lo":128.0868567},{"c":"A10025747","s":"정촌대경파미르아파트-a10025747","q":1,"n":"정촌대경파미르아파트","sd":"경상남도","sg":"진주시","d":"예하리","a":"경상남도 진주시 삼일로106번길 8","h":1465,"b":22,"y":2019,"ht":"개별난방","mt":"위탁관리","ma":154339,"lm":"2026-05","tf":1803,"cf":777,"rf":370,"la":35.1274244,"lo":128.1002844},{"c":"A10025006","s":"정촌올리움-a10025006","q":1,"n":"정촌올리움","sd":"경상남도","sg":"진주시","d":"예하리","a":"경상남도 진주시 삼일로 12","h":794,"b":6,"y":2020,"ht":"개별난방","mt":"위탁관리","ma":73693,"lm":"2026-05","tf":1277,"cf":864,"rf":0,"la":35.123389,"lo":128.0986266},{"c":"A66030001","s":"제일풍경채-a66030001","q":0,"n":"제일풍경채","sd":"경상남도","sg":"진주시","d":"가좌동","a":"경상남도 진주시 가좌안골길21번길 5","h":218,"b":4,"y":2007,"ht":"개별난방","mt":"위탁관리","ma":27303,"lm":"2026-04","tf":2324,"cf":1143,"rf":396,"la":35.1540965,"lo":128.1081667},{"c":"A66077104","s":"주약현대아파트-a66077104","q":1,"n":"주약현대아파트","sd":"경상남도","sg":"진주시","d":"주약동","a":"경상남도 진주시 진주대로815번길 11","h":835,"b":18,"y":2000,"ht":"개별난방","mt":"위탁관리","ma":89390,"lm":"2026-05","tf":1743,"cf":879,"rf":270,"la":35.1721251,"lo":128.092952},{"c":"A10024715","s":"중흥s클래스센트럴시티c2-a10024715","q":1,"n":"중흥S클래스센트럴시티C2","sd":"경상남도","sg":"진주시","d":"충무공동","a":"경상남도 진주시 에나로 190","h":560,"b":8,"y":2020,"ht":"지역난방","mt":"위탁관리","ma":76090,"lm":"2026-05","tf":2053,"cf":780,"rf":151,"la":35.1733886,"lo":128.1434295},{"c":"A10024714","s":"중흥s클래스센트럴시티c3-a10024714","q":0,"n":"중흥S클래스센트럴시티C3","sd":"경상남도","sg":"진주시","d":"충무공동","a":"경상남도 진주시 에나로175번길 12","h":333,"b":4,"y":2020,"ht":"지역난방","mt":"위탁관리","ma":39214,"lm":"2026-04","tf":2534,"cf":1164,"rf":150,"la":35.1734891,"lo":128.1451285},{"c":"A10022096","s":"진주-롯데인벤스-a10022096","q":1,"n":"진주 롯데인벤스","sd":"경상남도","sg":"진주시","d":"평안동","a":"경상남도 진주시 평안동 47- 진주 롯데인벤스","h":143,"b":2,"y":2008,"ht":"개별난방","mt":"자치관리","ma":25727,"lm":"2026-05","tf":1662,"cf":925,"rf":100,"la":35.197846,"lo":128.0832124},{"c":"A10024438","s":"진주-일동미라주-아파트-a10024438","q":1,"n":"진주 일동미라주 아파트","sd":"경상남도","sg":"진주시","d":"강남동","a":"경상남도 진주시 진주대로 881","h":394,"b":3,"y":2021,"ht":"개별난방","mt":"위탁관리","ma":45992,"lm":"2026-05","tf":1735,"cf":811,"rf":92,"la":35.1838887,"lo":128.0882602},{"c":"A10024693","s":"진주-중흥s-클래스-더퍼스트-a10024693","q":1,"n":"진주 중흥S-클래스 더퍼스트","sd":"경상남도","sg":"진주시","d":"충무공동","a":"경상남도 진주시 충의로 146","h":726,"b":10,"y":2020,"ht":"지역난방","mt":"위탁관리","ma":91752,"lm":"2026-05","tf":2272,"cf":933,"rf":150,"la":35.1762501,"lo":128.1503593},{"c":"A66076105","s":"진주가좌1주공-a66076105","q":1,"n":"진주가좌1주공","sd":"경상남도","sg":"진주시","d":"가좌동","a":"경상남도 진주시 가호로 26","h":627,"b":3,"y":1993,"ht":"중앙난방","mt":"위탁관리","ma":18455,"lm":"2026-05","tf":2806,"cf":1857,"rf":0,"la":35.1616597,"lo":128.1098391},{"c":"A66078904","s":"진주가좌주공2아파트-a66078904","q":1,"n":"진주가좌주공2아파트","sd":"경상남도","sg":"진주시","d":"가좌동","a":"경상남도 진주시 가호로 26","h":1530,"b":13,"y":1993,"ht":"개별난방","mt":"위탁관리","ma":97534,"lm":"2026-05","tf":1488,"cf":769,"rf":200,"la":35.1616597,"lo":128.1098391},{"c":"A10026663","s":"진주라온프라이빗아파트-a10026663","q":1,"n":"진주라온프라이빗아파트","sd":"경상남도","sg":"진주시","d":"충무공동","a":"경상남도 진주시 대밭골로 92","h":422,"b":6,"y":2017,"ht":"지역난방","mt":"위탁관리","ma":46663,"lm":"2026-05","tf":2104,"cf":965,"rf":150,"la":35.1808669,"lo":128.1503392},{"c":"A66084101","s":"진주문산코아루-a66084101","q":0,"n":"진주문산코아루","sd":"경상남도","sg":"진주시","d":"소문리","a":"경상남도 진주시 월아산로1117번길 5","h":520,"b":9,"y":2010,"ht":"개별난방","mt":"위탁관리","ma":65825,"lm":"2026-04","tf":1673,"cf":820,"rf":163,"la":35.1696202,"lo":128.1612005},{"c":"A66084102","s":"진주문산파란채-a66084102","q":1,"n":"진주문산파란채","sd":"경상남도","sg":"진주시","d":"삼곡리","a":"경상남도 진주시 월아산로1048번길 15","h":351,"b":6,"y":2010,"ht":"개별난방","mt":"위탁관리","ma":40349,"lm":"2026-05","tf":1736,"cf":890,"rf":200,"la":35.1653999,"lo":128.1657289},{"c":"A10025899","s":"진주문산lh아파트-a10025899","q":1,"n":"진주문산LH아파트","sd":"경상남도","sg":"진주시","d":"삼곡리","a":"경상남도 진주시 월아산로 1047-14","h":210,"b":2,"y":2018,"ht":"개별난방","mt":"위탁관리","ma":9247,"lm":"2026-05","tf":2278,"cf":1909,"rf":0,"la":35.1642989,"lo":128.1624322},{"c":"A66072301","s":"진주센트럴자이-a66072301","q":0,"n":"진주센트럴자이","sd":"경상남도","sg":"진주시","d":"상평동","a":"경상남도 진주시 도동천로 48","h":401,"b":6,"y":2013,"ht":"개별난방","mt":"위탁관리","ma":45789,"lm":"2026-04","tf":2412,"cf":1307,"rf":414,"la":35.1777812,"lo":128.1056459},{"c":"A10024143","s":"진주옥봉엘에이치아파트-a10024143","q":1,"n":"진주옥봉엘에이치아파트","sd":"경상남도","sg":"진주시","d":"옥봉동","a":"경상남도 진주시 진산로 20","h":500,"b":3,"y":2021,"ht":"개별난방","mt":"위탁관리","ma":32158,"lm":"2026-05","tf":1486,"cf":1173,"rf":0,"la":35.1935628,"lo":128.0946371},{"c":"A10026632","s":"진주우방아이유쉘-a10026632","q":0,"n":"진주우방아이유쉘","sd":"경상남도","sg":"진주시","d":"예하리","a":"경상남도 진주시 삼일로 13","h":430,"b":5,"y":2017,"ht":"개별난방","mt":"위탁관리","ma":48762,"lm":"2026-04","tf":1947,"cf":1023,"rf":97,"la":35.121935,"lo":128.0975849},{"c":"A10020737","s":"진주의봄-아파트-a10020737","q":1,"n":"진주의봄 아파트","sd":"경상남도","sg":"진주시","d":"가좌동","a":"경상남도 진주시 가좌동 2033- 진주의봄 아파트","h":773,"b":12,"y":2025,"ht":"개별난방","mt":"위탁관리","ma":63408,"lm":"2026-05","tf":1649,"cf":951,"rf":0,"la":35.1494111,"lo":128.1110078},{"c":"A66078608","s":"진주초장엠코타운더이스턴파크-a66078608","q":1,"n":"진주초장엠코타운더이스턴파크","sd":"경상남도","sg":"진주시","d":"초전동","a":"경상남도 진주시 초북로 77","h":883,"b":10,"y":2014,"ht":"개별난방","mt":"위탁관리","ma":95361,"lm":"2026-05","tf":1860,"cf":967,"rf":150,"la":35.2132177,"lo":128.1086757},{"c":"A10025922","s":"진주초장이지더원아파트-a10025922","q":0,"n":"진주초장이지더원아파트","sd":"경상남도","sg":"진주시","d":"초전동","a":"경상남도 진주시 초장로 120","h":543,"b":6,"y":2018,"ht":"개별난방","mt":"위탁관리","ma":62019,"lm":"2026-04","tf":1885,"cf":1008,"rf":90,"la":35.2104111,"lo":128.1100012},{"c":"A66078606","s":"진주초전푸르지오1단지-a66078606","q":1,"n":"진주초전푸르지오1단지","sd":"경상남도","sg":"진주시","d":"초전동","a":"경상남도 진주시 초장로14번길 27","h":812,"b":9,"y":2009,"ht":"개별난방","mt":"위탁관리","ma":118185,"lm":"2026-05","tf":1678,"cf":725,"rf":190,"la":35.2045126,"lo":128.1128736},{"c":"A10025368","s":"진주평거-우방아이유쉘-스카이팰리스-a10025368","q":0,"n":"진주평거 우방아이유쉘 스카이팰리스","sd":"경상남도","sg":"진주시","d":"평거동","a":"경상남도 진주시 진양호로 221","h":339,"b":2,"y":2019,"ht":"개별난방","mt":"위탁관리","ma":40464,"lm":"2026-04","tf":2036,"cf":968,"rf":227,"la":35.1741055,"lo":128.060242},{"c":"A66077710","s":"진주평거2-a66077710","q":1,"n":"진주평거2","sd":"경상남도","sg":"진주시","d":"평거동","a":"경상남도 진주시 진양호로125번길 6","h":480,"b":8,"y":1991,"ht":"개별난방","mt":"위탁관리","ma":20121,"lm":"2026-05","tf":1144,"cf":997,"rf":0,"la":35.1690323,"lo":128.0538296},{"c":"A66077410","s":"진주평거5단지-a66077410","q":1,"n":"진주평거5단지","sd":"경상남도","sg":"진주시","d":"평거동","a":"경상남도 진주시 새평거로 70","h":826,"b":11,"y":2012,"ht":"개별난방","mt":"위탁관리","ma":78159,"lm":"2026-05","tf":1285,"cf":850,"rf":0,"la":35.1666301,"lo":128.0564378},{"c":"A10027160","s":"진주평거엘크루아파트-a10027160","q":1,"n":"진주평거엘크루아파트","sd":"경상남도","sg":"진주시","d":"평거동","a":"경상남도 진주시 새평거로 112","h":472,"b":10,"y":2016,"ht":"개별난방","mt":"위탁관리","ma":53228,"lm":"2026-05","tf":2021,"cf":1086,"rf":120,"la":35.1689247,"lo":128.0606508},{"c":"A10024836","s":"진주포레스트부영아파트-a10024836","q":0,"n":"진주포레스트부영아파트","sd":"경상남도","sg":"진주시","d":"충무공동","a":"경상남도 진주시 영천강로 60","h":840,"b":11,"y":2020,"ht":"지역난방","mt":"위탁관리","ma":67425,"lm":"2026-04","tf":2247,"cf":917,"rf":114,"la":35.1684314,"lo":128.1378408},{"c":"A66079304","s":"진주푸르지오1단지-a66079304","q":1,"n":"진주푸르지오1단지","sd":"경상남도","sg":"진주시","d":"장사리","a":"경상남도 진주시 덕의길 15","h":475,"b":8,"y":2007,"ht":"개별난방","mt":"위탁관리","ma":55643,"lm":"2026-05","tf":1801,"cf":880,"rf":280,"la":35.218911,"lo":128.1460287},{"c":"A66079301","s":"진주푸르지오2단지-a66079301","q":0,"n":"진주푸르지오2단지","sd":"경상남도","sg":"진주시","d":"장사리","a":"경상남도 진주시 덕의길 11","h":337,"b":5,"y":2007,"ht":"개별난방","mt":"위탁관리","ma":43091,"lm":"2026-04","tf":1911,"cf":976,"rf":300,"la":35.2178013,"lo":128.147277},{"c":"A10025475","s":"진주혁신-중흥-s-클래스-12단지-a10025475","q":1,"n":"진주혁신 중흥 s-클래스(12단지)","sd":"경상남도","sg":"진주시","d":"충무공동","a":"경상남도 진주시 소호로19번길 11","h":1143,"b":16,"y":2019,"ht":"지역난방","mt":"위탁관리","ma":136098,"lm":"2026-05","tf":1918,"cf":737,"rf":140,"la":35.1686565,"lo":128.1346297},{"c":"A10026085","s":"진주혁신대방노블랜드1차-a10026085","q":1,"n":"진주혁신대방노블랜드1차","sd":"경상남도","sg":"진주시","d":"충무공동","a":"경상남도 진주시 사들로 61","h":743,"b":9,"y":2018,"ht":"지역난방","mt":"위탁관리","ma":89680,"lm":"2026-05","tf":2266,"cf":857,"rf":150,"la":35.1734186,"lo":128.1476537},{"c":"A66084105","s":"진주혁신더힐아파트-a66084105","q":1,"n":"진주혁신더힐아파트","sd":"경상남도","sg":"진주시","d":"충무공동","a":"경상남도 진주시 충의로 67","h":600,"b":7,"y":2014,"ht":"지역난방","mt":"자치관리","ma":64750,"lm":"2026-05","tf":2220,"cf":859,"rf":330,"la":35.1785375,"lo":128.1524232},{"c":"A66092110","s":"진주혁신도시-센텀리버파크-a66092110","q":1,"n":"진주혁신도시 센텀리버파크","sd":"경상남도","sg":"진주시","d":"충무공동","a":"경상남도 진주시 사들로 157","h":742,"b":9,"y":2013,"ht":"지역난방","mt":"위탁관리","ma":104916,"lm":"2026-05","tf":1645,"cf":649,"rf":150,"la":35.1821029,"lo":128.1477557},{"c":"A10024718","s":"진주혁신중흥s클래스센트럴시티c-4-a10024718","q":1,"n":"진주혁신중흥S클래스센트럴시티C-4","sd":"경상남도","sg":"진주시","d":"충무공동","a":"경상남도 진주시 에나로175번길 11","h":444,"b":5,"y":2020,"ht":"지역난방","mt":"위탁관리","ma":51537,"lm":"2026-05","tf":2185,"cf":894,"rf":98,"la":35.1743881,"lo":128.1458276},{"c":"A66084103","s":"진주혁신코오롱하늘채-a66084103","q":1,"n":"진주혁신코오롱하늘채","sd":"경상남도","sg":"진주시","d":"충무공동","a":"경상남도 진주시 사들로 126","h":1037,"b":12,"y":2014,"ht":"지역난방","mt":"위탁관리","ma":147534,"lm":"2026-05","tf":1590,"cf":594,"rf":200,"la":35.17857,"lo":128.1498009},{"c":"A10020310","s":"철도문화공원극동스타클래스-a10020310","q":0,"n":"철도문화공원극동스타클래스","sd":"경상남도","sg":"진주시","d":"주약동","a":"경상남도 진주시 주약동 183-1 철도문화공원극동스타클래스","h":166,"b":1,"y":2025,"ht":"개별난방","mt":"위탁관리","ma":19685,"lm":"2026-04","tf":2049,"cf":1340,"rf":0,"la":35.1780937,"lo":128.0908791},{"c":"A66078609","s":"초전-해모로-루비채-2단지-a66078609","q":1,"n":"초전 해모로 루비채 2단지","sd":"경상남도","sg":"진주시","d":"초전동","a":"경상남도 진주시 초북로 88","h":564,"b":8,"y":2014,"ht":"개별난방","mt":"위탁관리","ma":47205,"lm":"2026-05","tf":2589,"cf":1246,"rf":283,"la":35.2147855,"lo":128.1078341},{"c":"A66098501","s":"초전일동-a66098501","q":1,"n":"초전일동","sd":"경상남도","sg":"진주시","d":"초전동","a":"경상남도 진주시 초전북로 20-1","h":180,"b":1,"y":1994,"ht":"개별난방","mt":"위탁관리","ma":17169,"lm":"2026-05","tf":1219,"cf":716,"rf":270,"la":35.2074484,"lo":128.1094653},{"c":"A66078605","s":"초전청구타운-a66078605","q":1,"n":"초전청구타운","sd":"경상남도","sg":"진주시","d":"초전동","a":"경상남도 진주시 대신로475번길 16-5","h":494,"b":6,"y":1997,"ht":"개별난방","mt":"위탁관리","ma":48259,"lm":"2026-05","tf":1829,"cf":941,"rf":289,"la":35.2026027,"lo":128.1125397},{"c":"A66078607","s":"초전푸르지오2단지-a66078607","q":1,"n":"초전푸르지오2단지","sd":"경상남도","sg":"진주시","d":"초전동","a":"경상남도 진주시 초장로14번길 29","h":830,"b":10,"y":2010,"ht":"개별난방","mt":"위탁관리","ma":118830,"lm":"2026-05","tf":1831,"cf":829,"rf":205,"la":35.2067748,"lo":128.1117927},{"c":"A66078610","s":"초전해모로루비채4단지-a66078610","q":1,"n":"초전해모로루비채4단지","sd":"경상남도","sg":"진주시","d":"초전동","a":"경상남도 진주시 초북로 55","h":774,"b":8,"y":2014,"ht":"개별난방","mt":"위탁관리","ma":90433,"lm":"2026-05","tf":1767,"cf":862,"rf":170,"la":35.2121797,"lo":128.1095874},{"c":"A66078404","s":"초전현대-a66078404","q":1,"n":"초전현대","sd":"경상남도","sg":"진주시","d":"초전동","a":"경상남도 진주시 초전남로 60,경상남도 진주시 초전남로 46","h":491,"b":5,"y":1997,"ht":"개별난방","mt":"위탁관리","ma":45031,"lm":"2026-05","tf":2002,"cf":1050,"rf":362,"la":35.2005539,"lo":128.1143021},{"c":"A66078503","s":"초전흥한황토방아파트-a66078503","q":1,"n":"초전흥한황토방아파트","sd":"경상남도","sg":"진주시","d":"초전동","a":"경상남도 진주시 초전남로 30","h":456,"b":8,"y":2001,"ht":"개별난방","mt":"위탁관리","ma":46153,"lm":"2026-05","tf":1855,"cf":930,"rf":320,"la":35.1991818,"lo":128.114728},{"c":"A10021424","s":"촉석아파트-a10021424","q":0,"n":"촉석아파트","sd":"경상남도","sg":"진주시","d":"상평동","a":"경상남도 진주시 상평동 219-91 촉석아파트","h":166,"b":6,"y":1980,"ht":"개별난방","mt":"자치관리","ma":11977,"lm":"2026-04","tf":632,"cf":270,"rf":214,"la":35.1778773,"lo":128.1077288},{"c":"A66098801","s":"칠암대덕-a66098801","q":0,"n":"칠암대덕","sd":"경상남도","sg":"진주시","d":"칠암동","a":"경상남도 진주시 진주대로942번길 12","h":159,"b":1,"y":2004,"ht":"개별난방","mt":"위탁관리","ma":12228,"lm":"2026-04","tf":2090,"cf":1064,"rf":399,"la":35.1843866,"lo":128.0901013},{"c":"A66098703","s":"칠암한주-a66098703","q":1,"n":"칠암한주","sd":"경상남도","sg":"진주시","d":"칠암동","a":"경상남도 진주시 강남로 101","h":190,"b":1,"y":1995,"ht":"개별난방","mt":"위탁관리","ma":15042,"lm":"2026-05","tf":2414,"cf":1337,"rf":342,"la":35.1775193,"lo":128.0972657},{"c":"A66098802","s":"칠암현대-a66098802","q":0,"n":"칠암현대","sd":"경상남도","sg":"진주시","d":"칠암동","a":"경상남도 진주시 강남로255번길 18","h":190,"b":3,"y":1985,"ht":"개별난방","mt":"위탁관리","ma":22810,"lm":"2026-04","tf":1331,"cf":631,"rf":212,"la":35.1871399,"lo":128.0890028},{"c":"A10021677","s":"태완노블리안-a10021677","q":0,"n":"태완노블리안","sd":"경상남도","sg":"진주시","d":"창촌리","a":"경상남도 진주시 일반성면 창촌리 176- 태완노블리안","h":110,"b":2,"y":2007,"ht":"","mt":"자치관리","ma":9091,"lm":"2026-04","tf":1563,"cf":649,"rf":232,"la":35.1727056,"lo":128.2861818},{"c":"A66098901","s":"판문현대-a66098901","q":1,"n":"판문현대","sd":"경상남도","sg":"진주시","d":"판문동","a":"경상남도 진주시 진양호로51번길 6-7","h":294,"b":3,"y":1992,"ht":"개별난방","mt":"위탁관리","ma":30382,"lm":"2026-05","tf":1767,"cf":953,"rf":229,"la":35.1681164,"lo":128.0461232},{"c":"A66090805","s":"평거1차현대-a66090805","q":1,"n":"평거1차현대","sd":"경상남도","sg":"진주시","d":"신안동","a":"경상남도 진주시 평거로115번길 5","h":441,"b":3,"y":1993,"ht":"개별난방","mt":"위탁관리","ma":44407,"lm":"2026-05","tf":1571,"cf":750,"rf":285,"la":35.1800154,"lo":128.0678613},{"c":"A66090804","s":"평거2차현대아파트-a66090804","q":1,"n":"평거2차현대아파트","sd":"경상남도","sg":"진주시","d":"신안동","a":"경상남도 진주시 신안들말길 58","h":402,"b":5,"y":1994,"ht":"개별난방","mt":"위탁관리","ma":44001,"lm":"2026-05","tf":1438,"cf":605,"rf":291,"la":35.1805972,"lo":128.0667016},{"c":"A10022212","s":"평거대화리네르빌-a10022212","q":1,"n":"평거대화리네르빌","sd":"경상남도","sg":"진주시","d":"평거동","a":"경상남도 진주시 평거동 297-1 평거대화리네르빌","h":114,"b":2,"y":2004,"ht":"개별난방","mt":"자치관리","ma":11232,"lm":"2026-05","tf":1853,"cf":962,"rf":183,"la":35.1733132,"lo":128.0590515},{"c":"A66099105","s":"평거주공1차-a66099105","q":0,"n":"평거주공1차","sd":"경상남도","sg":"진주시","d":"평거동","a":"경상남도 진주시 진양호로185번길 7","h":340,"b":7,"y":1988,"ht":"개별난방","mt":"위탁관리","ma":17695,"lm":"2026-04","tf":1397,"cf":1062,"rf":131,"la":35.1718899,"lo":128.0574504},{"c":"A10021771","s":"평거하우스토리아파트-a10021771","q":0,"n":"평거하우스토리아파트","sd":"경상남도","sg":"진주시","d":"평거동","a":"경상남도 진주시 평거동 150-4 평거하우스토리아파트","h":115,"b":4,"y":2009,"ht":"개별난방","mt":"위탁관리","ma":17434,"lm":"2026-04","tf":1909,"cf":965,"rf":153,"la":35.1754381,"lo":128.0600831},{"c":"A66077408","s":"평거휴먼시아3단지-a66077408","q":1,"n":"평거휴먼시아3단지","sd":"경상남도","sg":"진주시","d":"평거동","a":"경상남도 진주시 새평거로 111","h":588,"b":13,"y":2011,"ht":"개별난방","mt":"위탁관리","ma":86349,"lm":"2026-05","tf":1510,"cf":725,"rf":197,"la":35.170563,"lo":128.0591628},{"c":"A66077409","s":"평거휴먼시아4단지-a66077409","q":1,"n":"평거휴먼시아4단지","sd":"경상남도","sg":"진주시","d":"평거동","a":"경상남도 진주시 새평거로 75","h":706,"b":13,"y":2011,"ht":"개별난방","mt":"위탁관리","ma":97069,"lm":"2026-05","tf":1295,"cf":656,"rf":85,"la":35.1679917,"lo":128.0553971},{"c":"A10025102","s":"포레나신진주아파트-a10025102","q":1,"n":"포레나신진주아파트","sd":"경상남도","sg":"진주시","d":"가좌동","a":"경상남도 진주시 진주역로96번길 15","h":424,"b":3,"y":2019,"ht":"개별난방","mt":"위탁관리","ma":50766,"lm":"2026-05","tf":1841,"cf":955,"rf":120,"la":35.150768,"lo":128.1150139},{"c":"A10023967","s":"프리미어웰가-a10023967","q":1,"n":"프리미어웰가","sd":"경상남도","sg":"진주시","d":"가좌동","a":"경상남도 진주시 개양로 67","h":702,"b":8,"y":2021,"ht":"개별난방","mt":"위탁관리","ma":57129,"lm":"2026-05","tf":1909,"cf":1082,"rf":0,"la":35.1559303,"lo":128.1131764},{"c":"A10022231","s":"하대-임광아파트-a10022231","q":1,"n":"하대 임광아파트","sd":"경상남도","sg":"진주시","d":"하대동","a":"경상남도 진주시 하대동 104-3 하대 임광아파트","h":143,"b":2,"y":1989,"ht":"개별난방","mt":"위탁관리","ma":10825,"lm":"2026-05","tf":2364,"cf":1360,"rf":464,"la":35.1894478,"lo":128.1258609},{"c":"A66033001","s":"하대대경-a66033001","q":0,"n":"하대대경","sd":"경상남도","sg":"진주시","d":"하대동","a":"경상남도 진주시 도동로264번길 31","h":150,"b":1,"y":1992,"ht":"개별난방","mt":"위탁관리","ma":11901,"lm":"2026-04","tf":1795,"cf":1084,"rf":441,"la":35.1942283,"lo":128.1251708},{"c":"A66033005","s":"하대대림-a66033005","q":0,"n":"하대대림","sd":"경상남도","sg":"진주시","d":"하대동","a":"경상남도 진주시 도동천로 310","h":239,"b":1,"y":1991,"ht":"개별난방","mt":"위탁관리","ma":19498,"lm":"2026-04","tf":2035,"cf":986,"rf":279,"la":35.1939585,"lo":128.1273094},{"c":"A66033004","s":"하대대영-a66033004","q":0,"n":"하대대영","sd":"경상남도","sg":"진주시","d":"하대동","a":"경상남도 진주시 말티고개로 102-5","h":210,"b":2,"y":1992,"ht":"개별난방","mt":"위탁관리","ma":20306,"lm":"2026-04","tf":1271,"cf":776,"rf":270,"la":35.1961279,"lo":128.112588},{"c":"A66099301","s":"하대쌍용-a66099301","q":0,"n":"하대쌍용","sd":"경상남도","sg":"진주시","d":"하대동","a":"경상남도 진주시 말티고개로108번길 5","h":156,"b":2,"y":1996,"ht":"개별난방","mt":"위탁관리","ma":14571,"lm":"2026-04","tf":1973,"cf":1055,"rf":208,"la":35.1961745,"lo":128.1135896},{"c":"A66099302","s":"하대일신-a66099302","q":1,"n":"하대일신","sd":"경상남도","sg":"진주시","d":"하대동","a":"경상남도 진주시 하대로34번길 10","h":258,"b":3,"y":1991,"ht":"개별난방","mt":"위탁관리","ma":26235,"lm":"2026-05","tf":1498,"cf":661,"rf":302,"la":35.1933782,"lo":128.1146301},{"c":"A66033008","s":"하대주공-a66033008","q":1,"n":"하대주공","sd":"경상남도","sg":"진주시","d":"하대동","a":"경상남도 진주시 상대로 125","h":500,"b":10,"y":1982,"ht":"개별난방","mt":"자치관리","ma":23200,"lm":"2026-05","tf":1206,"cf":866,"rf":119,"la":35.1852677,"lo":128.1263428},{"c":"A66033007","s":"하대한보3차-a66033007","q":1,"n":"하대한보3차","sd":"경상남도","sg":"진주시","d":"하대동","a":"경상남도 진주시 남강로 1399","h":288,"b":2,"y":1993,"ht":"개별난방","mt":"위탁관리","ma":27291,"lm":"2026-05","tf":1567,"cf":798,"rf":242,"la":35.1855065,"lo":128.1282969},{"c":"A66099502","s":"하대한보타워-a66099502","q":1,"n":"하대한보타워","sd":"경상남도","sg":"진주시","d":"하대동","a":"경상남도 진주시 모덕로306번길 2","h":155,"b":1,"y":1992,"ht":"개별난방","mt":"위탁관리","ma":11613,"lm":"2026-05","tf":1434,"cf":1014,"rf":181,"la":35.1887899,"lo":128.1270313},{"c":"A66033002","s":"하대한보힐타워-a66033002","q":1,"n":"하대한보힐타워","sd":"경상남도","sg":"진주시","d":"하대동","a":"경상남도 진주시 상대로143번길 11-2","h":152,"b":1,"y":1992,"ht":"개별난방","mt":"위탁관리","ma":12282,"lm":"2026-05","tf":1457,"cf":1069,"rf":136,"la":35.1861023,"lo":128.1271425},{"c":"A66077803","s":"하대현대-a66077803","q":1,"n":"하대현대","sd":"경상남도","sg":"진주시","d":"하대동","a":"경상남도 진주시 하대로 142","h":1108,"b":7,"y":1996,"ht":"개별난방","mt":"위탁관리","ma":92605,"lm":"2026-05","tf":2153,"cf":1025,"rf":432,"la":35.1922774,"lo":128.1260185},{"c":"A66099103","s":"하영그린맨션-a66099103","q":1,"n":"하영그린맨션","sd":"경상남도","sg":"진주시","d":"평거동","a":"경상남도 진주시 진양호로97번길 8-3","h":198,"b":2,"y":1992,"ht":"개별난방","mt":"위탁관리","ma":18260,"lm":"2026-05","tf":1331,"cf":831,"rf":259,"la":35.1682788,"lo":128.0509576},{"c":"A66099101","s":"하영무지개-a66099101","q":1,"n":"하영무지개","sd":"경상남도","sg":"진주시","d":"평거동","a":"경상남도 진주시 진양호로 153-1","h":190,"b":1,"y":1993,"ht":"개별난방","mt":"위탁관리","ma":17117,"lm":"2026-05","tf":1325,"cf":868,"rf":242,"la":35.1697454,"lo":128.0554453},{"c":"A10027818","s":"한림풀에버-a10027818","q":1,"n":"한림풀에버","sd":"경상남도","sg":"진주시","d":"충무공동","a":"경상남도 진주시 소호로 78","h":1421,"b":19,"y":2015,"ht":"지역난방","mt":"위탁관리","ma":156842,"lm":"2026-05","tf":2051,"cf":796,"rf":180,"la":35.1714478,"lo":128.1332555},{"c":"A66077202","s":"한보은빛마을-a66077202","q":1,"n":"한보은빛마을","sd":"경상남도","sg":"진주시","d":"주약동","a":"경상남도 진주시 천수로 30","h":516,"b":7,"y":2002,"ht":"개별난방","mt":"위탁관리","ma":66202,"lm":"2026-05","tf":1571,"cf":832,"rf":190,"la":35.1711135,"lo":128.0933799},{"c":"A66099102","s":"한보하이타운-a66099102","q":1,"n":"한보하이타운","sd":"경상남도","sg":"진주시","d":"평거동","a":"경상남도 진주시 순환로553번길 7","h":198,"b":1,"y":1995,"ht":"개별난방","mt":"위탁관리","ma":19324,"lm":"2026-05","tf":1361,"cf":800,"rf":302,"la":35.1726171,"lo":128.0592871},{"c":"A66077305","s":"한주럭키타운-a66077305","q":1,"n":"한주럭키타운","sd":"경상남도","sg":"진주시","d":"주약동","a":"경상남도 진주시 진주대로 859","h":936,"b":13,"y":1990,"ht":"개별난방","mt":"자치관리","ma":102070,"lm":"2026-05","tf":1706,"cf":710,"rf":212,"la":35.1763989,"lo":128.0908507},{"c":"A66090501","s":"한주파크맨션-a66090501","q":0,"n":"한주파크맨션","sd":"경상남도","sg":"진주시","d":"신안동","a":"경상남도 진주시 남강로 479","h":195,"b":1,"y":1990,"ht":"개별난방","mt":"위탁관리","ma":18524,"lm":"2026-04","tf":1375,"cf":963,"rf":212,"la":35.1812916,"lo":128.0725702},{"c":"A66025003","s":"한주한보타운-a66025003","q":1,"n":"한주한보타운","sd":"경상남도","sg":"진주시","d":"강남동","a":"경상남도 진주시 망경로296번길 17","h":279,"b":2,"y":1995,"ht":"개별난방","mt":"위탁관리","ma":20554,"lm":"2026-05","tf":2869,"cf":1223,"rf":234,"la":35.1841331,"lo":128.0866937},{"c":"A10026436","s":"혁신도시엔에이치에프10단지-a10026436","q":1,"n":"혁신도시엔에이치에프10단지","sd":"경상남도","sg":"진주시","d":"충무공동","a":"경상남도 진주시 에나로228번길 10","h":404,"b":5,"y":2018,"ht":"지역난방","mt":"위탁관리","ma":59541,"lm":"2026-05","tf":1399,"cf":719,"rf":0,"la":35.1709635,"lo":128.1430078},{"c":"A10027776","s":"혁신도시엘에이치아파트8단지-a10027776","q":1,"n":"혁신도시엘에이치아파트8단지","sd":"경상남도","sg":"진주시","d":"충무공동","a":"경상남도 진주시 사들로 83,경상남도 진주시 충의로 67","h":802,"b":9,"y":2015,"ht":"지역난방","mt":"위탁관리","ma":67885,"lm":"2026-05","tf":2044,"cf":922,"rf":106,"la":35.1719818,"lo":128.1465097},{"c":"A10026236","s":"혁신도시lh아파트3단지-a10026236","q":1,"n":"혁신도시LH아파트3단지","sd":"경상남도","sg":"진주시","d":"충무공동","a":"경상남도 진주시 대밭골로 91","h":1256,"b":11,"y":2018,"ht":"지역난방","mt":"위탁관리","ma":74175,"lm":"2026-05","tf":1454,"cf":876,"rf":0,"la":35.1806152,"lo":128.1527874},{"c":"A66029001","s":"현대성우트리팰리스-a66029001","q":1,"n":"현대성우트리팰리스","sd":"경상남도","sg":"진주시","d":"주약동","a":"경상남도 진주시 진주대로879번길 19","h":160,"b":1,"y":2006,"ht":"개별난방","mt":"위탁관리","ma":24164,"lm":"2026-05","tf":1986,"cf":1106,"rf":111,"la":35.1780359,"lo":128.089948},{"c":"A66031002","s":"호탄대경빌라트-a66031002","q":1,"n":"호탄대경빌라트","sd":"경상남도","sg":"진주시","d":"호탄동","a":"경상남도 진주시 가호로 79","h":304,"b":4,"y":2000,"ht":"개별난방","mt":"위탁관리","ma":32858,"lm":"2026-05","tf":1688,"cf":890,"rf":222,"la":35.164843,"lo":128.1141779},{"c":"A66031001","s":"호탄삼성-a66031001","q":1,"n":"호탄삼성","sd":"경상남도","sg":"진주시","d":"호탄동","a":"경상남도 진주시 동부로43번길 10-13","h":200,"b":2,"y":1996,"ht":"개별난방","mt":"위탁관리","ma":21138,"lm":"2026-05","tf":1902,"cf":1104,"rf":265,"la":35.1625344,"lo":128.1133929},{"c":"A10025629","s":"휴앤인-엘리시움-a10025629","q":1,"n":"휴앤인 엘리시움","sd":"경상남도","sg":"진주시","d":"충무공동","a":"경상남도 진주시 에나로 100","h":190,"b":1,"y":2019,"ht":"지역난방","mt":"위탁관리","ma":24017,"lm":"2026-05","tf":2194,"cf":1076,"rf":183,"la":35.1770128,"lo":128.1400508},{"c":"A66090802","s":"흥한타운1-a66090802","q":1,"n":"흥한타운1","sd":"경상남도","sg":"진주시","d":"신안동","a":"경상남도 진주시 진양호로328번길 4","h":225,"b":3,"y":1993,"ht":"개별난방","mt":"위탁관리","ma":25558,"lm":"2026-05","tf":1919,"cf":1034,"rf":302,"la":35.1814987,"lo":128.0673848},{"c":"A10025648","s":"힐스테이트-초전-a10025648","q":0,"n":"힐스테이트 초전","sd":"경상남도","sg":"진주시","d":"초전동","a":"경상남도 진주시 초북로 95","h":1070,"b":9,"y":2019,"ht":"개별난방","mt":"위탁관리","ma":123635,"lm":"2026-04","tf":1803,"cf":861,"rf":110,"la":35.2132895,"lo":128.1055378},{"c":"A10025172","s":"sky시티프라디움-a10025172","q":1,"n":"SKY시티프라디움","sd":"경상남도","sg":"진주시","d":"가좌동","a":"경상남도 진주시 개양로 100","h":869,"b":7,"y":2019,"ht":"개별난방","mt":"위탁관리","ma":98158,"lm":"2026-05","tf":1755,"cf":911,"rf":100,"la":35.1543923,"lo":128.116648}]