[{"c":"A48208004","s":"고읍주공6단지-a48208004","q":1,"n":"고읍주공6단지","sd":"경기도","sg":"양주시","d":"만송동","a":"경기도 양주시 고읍로 117-21","h":503,"b":5,"y":2010,"ht":"지역난방","mt":"위탁관리","ma":41265,"lm":"2026-05","tf":1825,"cf":1174,"rf":0,"la":37.7962283,"lo":127.0839053},{"c":"A48208005","s":"고읍휴먼시아7단지-a48208005","q":0,"n":"고읍휴먼시아7단지","sd":"경기도","sg":"양주시","d":"만송동","a":"경기도 양주시 고읍북로 78","h":773,"b":8,"y":2010,"ht":"지역난방","mt":"위탁관리","ma":61241,"lm":"2026-04","tf":1892,"cf":1164,"rf":0,"la":37.7961062,"lo":127.0858989},{"c":"A10025819","s":"금호산업제이드웰nhf-a10025819","q":1,"n":"금호산업제이드웰NHF","sd":"경기도","sg":"양주시","d":"옥정동","a":"경기도 양주시 옥정동로 106","h":526,"b":5,"y":2018,"ht":"지역난방","mt":"위탁관리","ma":79071,"lm":"2026-05","tf":1476,"cf":619,"rf":28,"la":37.8170797,"lo":127.1008659},{"c":"A10023240","s":"대광로제비앙-더메트로팰리스-a10023240","q":0,"n":"대광로제비앙 더메트로팰리스","sd":"경기도","sg":"양주시","d":"덕계동","a":"경기도 양주시 덕계로 137","h":424,"b":6,"y":2023,"ht":"지역난방","mt":"위탁관리","ma":50289,"lm":"2026-04","tf":2682,"cf":1152,"rf":110,"la":37.8169067,"lo":127.0546272},{"c":"A48283309","s":"대교산과내-a48283309","q":1,"n":"대교산과내","sd":"경기도","sg":"양주시","d":"방성리","a":"경기도 양주시 부흥로 1166-3","h":359,"b":5,"y":1999,"ht":"개별난방","mt":"위탁관리","ma":31978,"lm":"2026-05","tf":2704,"cf":1403,"rf":600,"la":37.7947805,"lo":127.0079554},{"c":"A48203002","s":"대방노블랜드-a48203002","q":1,"n":"대방노블랜드","sd":"경기도","sg":"양주시","d":"광사동","a":"경기도 양주시 부흥로 1898-4","h":499,"b":9,"y":2003,"ht":"개별난방","mt":"위탁관리","ma":51137,"lm":"2026-05","tf":2358,"cf":1091,"rf":427,"la":37.7904855,"lo":127.0748972},{"c":"A10023541","s":"대성베르힐옥정더센트로-a10023541","q":1,"n":"대성베르힐옥정더센트로","sd":"경기도","sg":"양주시","d":"옥정동","a":"경기도 양주시 독바위로 433","h":804,"b":9,"y":2022,"ht":"지역난방","mt":"위탁관리","ma":91891,"lm":"2026-05","tf":3543,"cf":954,"rf":200,"la":37.8122797,"lo":127.0847092},{"c":"A48270102","s":"덕계금용1차-a48270102","q":1,"n":"덕계금용1차","sd":"경기도","sg":"양주시","d":"덕계동","a":"경기도 양주시 평화로1429번길 43-10","h":188,"b":1,"y":1991,"ht":"개별난방","mt":"자치관리","ma":15575,"lm":"2026-05","tf":1394,"cf":943,"rf":145,"la":37.8201651,"lo":127.0433678},{"c":"A48270303","s":"덕계삼희-a48270303","q":1,"n":"덕계삼희","sd":"경기도","sg":"양주시","d":"덕계동","a":"경기도 양주시 덕계로 94-11","h":210,"b":1,"y":1996,"ht":"개별난방","mt":"자치관리","ma":11410,"lm":"2026-05","tf":1887,"cf":1251,"rf":290,"la":37.8181602,"lo":127.0597811},{"c":"A48270103","s":"덕계신도브래뉴아파트-a48270103","q":1,"n":"덕계신도브래뉴아파트","sd":"경기도","sg":"양주시","d":"덕계동","a":"경기도 양주시 평화로1475번길 161-14","h":249,"b":5,"y":2012,"ht":"개별난방","mt":"위탁관리","ma":28371,"lm":"2026-05","tf":2524,"cf":1244,"rf":400,"la":37.8254931,"lo":127.0415141},{"c":"A10023380","s":"덕계역-금강펜테리움센트럴파크-아파트-a10023380","q":1,"n":"덕계역 금강펜테리움센트럴파크 아파트","sd":"경기도","sg":"양주시","d":"덕계동","a":"경기도 양주시 고덕로 15","h":935,"b":6,"y":2023,"ht":"지역난방","mt":"위탁관리(직영+위탁)","ma":74423,"lm":"2026-05","tf":2771,"cf":1198,"rf":164,"la":37.8147798,"lo":127.048301},{"c":"A10020564","s":"덕정역서희스타힐스에듀포레뷰-a10020564","q":1,"n":"덕정역서희스타힐스에듀포레뷰","sd":"경기도","sg":"양주시","d":"덕정동","a":"경기도 양주시 덕정동 543- 덕정역서희스타힐스에듀포레뷰","h":931,"b":11,"y":2025,"ht":"개별난방","mt":"위탁관리","ma":82184,"lm":"2026-05","tf":2282,"cf":1327,"rf":0,"la":37.8478761,"lo":127.0671565},{"c":"A48206002","s":"덕정융보-a48206002","q":1,"n":"덕정융보","sd":"경기도","sg":"양주시","d":"덕정동","a":"경기도 양주시 독바위로 55","h":195,"b":1,"y":1992,"ht":"개별난방","mt":"위탁관리","ma":20629,"lm":"2026-05","tf":1509,"cf":777,"rf":217,"la":37.8367932,"lo":127.0636939},{"c":"A48079901","s":"덕정일성트루엘-a48079901","q":1,"n":"덕정일성트루엘","sd":"경기도","sg":"양주시","d":"덕정동","a":"경기도 양주시 덕정길 105","h":272,"b":6,"y":2011,"ht":"개별난방","mt":"위탁관리","ma":31361,"lm":"2026-05","tf":2340,"cf":1065,"rf":412,"la":37.8427002,"lo":127.0685566},{"c":"A48271203","s":"덕정주공3단지-a48271203","q":1,"n":"덕정주공3단지","sd":"경기도","sg":"양주시","d":"고암동","a":"경기도 양주시 고암길 275","h":1290,"b":13,"y":2001,"ht":"개별난방","mt":"위탁관리","ma":138478,"lm":"2026-05","tf":1958,"cf":733,"rf":500,"la":37.8337537,"lo":127.0706267},{"c":"A48271005","s":"덕정주공4단지-청담마을-a48271005","q":1,"n":"덕정주공4단지(청담마을)","sd":"경기도","sg":"양주시","d":"덕정동","a":"경기도 양주시 고암길 305-40","h":960,"b":12,"y":2001,"ht":"개별난방","mt":"위탁관리","ma":138806,"lm":"2026-05","tf":1685,"cf":702,"rf":330,"la":37.8331849,"lo":127.0671065},{"c":"A48271106","s":"덕정주공5단지-a48271106","q":1,"n":"덕정주공5단지","sd":"경기도","sg":"양주시","d":"덕정동","a":"경기도 양주시 고암길 354","h":1732,"b":20,"y":2000,"ht":"개별난방","mt":"위탁관리","ma":156648,"lm":"2026-05","tf":2199,"cf":925,"rf":689,"la":37.8340755,"lo":127.0660422},{"c":"A48270807","s":"덕정주공8단지-a48270807","q":1,"n":"덕정주공8단지","sd":"경기도","sg":"양주시","d":"고암동","a":"경기도 양주시 고암길 172-14","h":550,"b":7,"y":2006,"ht":"개별난방","mt":"위탁관리","ma":31071,"lm":"2026-05","tf":2526,"cf":1653,"rf":0,"la":37.8327163,"lo":127.075844},{"c":"A48270808","s":"덕정중흥s-클래스-a48270808","q":1,"n":"덕정중흥S-클래스","sd":"경기도","sg":"양주시","d":"고암동","a":"경기도 양주시 고암길 200","h":314,"b":5,"y":2011,"ht":"개별난방","mt":"위탁관리","ma":48272,"lm":"2026-05","tf":2151,"cf":943,"rf":350,"la":37.8345794,"lo":127.0758522},{"c":"A48283111","s":"동화1차장미-a48283111","q":1,"n":"동화1차장미","sd":"경기도","sg":"양주시","d":"복지리","a":"경기도 양주시 꿈나무로 299","h":443,"b":5,"y":1999,"ht":"개별난방","mt":"위탁관리","ma":45234,"lm":"2026-05","tf":2135,"cf":1113,"rf":272,"la":37.7837178,"lo":126.984073},{"c":"A48283105","s":"동화3차옥시죤아파트-a48283105","q":1,"n":"동화3차옥시죤아파트","sd":"경기도","sg":"양주시","d":"복지리","a":"경기도 양주시 꿈나무로 291","h":223,"b":2,"y":2003,"ht":"개별난방","mt":"위탁관리","ma":23885,"lm":"2026-05","tf":2237,"cf":1096,"rf":300,"la":37.7848418,"lo":126.983906},{"c":"A48293810","s":"동화5차-a48293810","q":1,"n":"동화5차","sd":"경기도","sg":"양주시","d":"가업리","a":"경기도 양주시 꿈나무로 320","h":439,"b":9,"y":2005,"ht":"개별난방","mt":"위탁관리","ma":44220,"lm":"2026-05","tf":2244,"cf":1185,"rf":400,"la":37.7820419,"lo":126.9816511},{"c":"A48293901","s":"동화6차옥시존-a48293901","q":1,"n":"동화6차옥시존","sd":"경기도","sg":"양주시","d":"복지리","a":"경기도 양주시 꿈나무로 325","h":205,"b":3,"y":2010,"ht":"개별난방","mt":"위탁관리","ma":23329,"lm":"2026-05","tf":1981,"cf":958,"rf":250,"la":37.7814985,"lo":126.9826123},{"c":"A10023519","s":"디에트르-프레스티지-아파트-a10023519","q":1,"n":"디에트르 프레스티지 아파트","sd":"경기도","sg":"양주시","d":"옥정동","a":"경기도 양주시 옥정로7길 34","h":1859,"b":15,"y":2022,"ht":"지역난방","mt":"위탁관리","ma":214078,"lm":"2026-05","tf":2287,"cf":758,"rf":185,"la":37.8299062,"lo":127.0897192},{"c":"A10023483","s":"디에트르센트럴시티-a10023483","q":1,"n":"디에트르센트럴시티","sd":"경기도","sg":"양주시","d":"덕계동","a":"경기도 양주시 회천중앙로 249","h":860,"b":7,"y":2022,"ht":"지역난방","mt":"위탁관리","ma":92503,"lm":"2026-05","tf":2434,"cf":897,"rf":142,"la":37.8204507,"lo":127.0517891},{"c":"A10022517","s":"라피아노-스위첸-2단지-a10022517","q":0,"n":"라피아노 스위첸 2단지","sd":"경기도","sg":"양주시","d":"옥정동","a":"경기도 양주시 옥정동 890-3 라피아노 스위첸 2단지","h":200,"b":16,"y":2024,"ht":"지역난방","mt":"위탁관리","ma":21448,"lm":"2026-04","tf":2917,"cf":1499,"rf":87,"la":37.8226649,"lo":127.0765191},{"c":"A10021211","s":"백석가야1차아파트-a10021211","q":1,"n":"백석가야1차아파트","sd":"경기도","sg":"양주시","d":"복지리","a":"경기도 양주시 백석읍 복지리 94- 백석가야1차아파트","h":210,"b":5,"y":1996,"ht":"개별난방","mt":"위탁관리","ma":13574,"lm":"2026-05","tf":1622,"cf":1135,"rf":147,"la":37.7861034,"lo":126.9937431},{"c":"A48283103","s":"백석가야3차-a48283103","q":1,"n":"백석가야3차","sd":"경기도","sg":"양주시","d":"복지리","a":"경기도 양주시 양주산성로 523","h":203,"b":4,"y":1999,"ht":"개별난방","mt":"위탁관리","ma":16374,"lm":"2026-05","tf":2575,"cf":1406,"rf":450,"la":37.7858143,"lo":126.9955509},{"c":"A48283113","s":"백석가야5차-a48283113","q":1,"n":"백석가야5차","sd":"경기도","sg":"양주시","d":"복지리","a":"경기도 양주시 호명로 103-14","h":497,"b":6,"y":2004,"ht":"개별난방","mt":"위탁관리","ma":63034,"lm":"2026-05","tf":1752,"cf":866,"rf":165,"la":37.7832689,"lo":126.9912278},{"c":"A48283506","s":"백석세아1차-a48283506","q":1,"n":"백석세아1차","sd":"경기도","sg":"양주시","d":"오산리","a":"경기도 양주시 꿈나무로 136","h":282,"b":2,"y":1993,"ht":"개별난방","mt":"위탁관리","ma":26300,"lm":"2026-05","tf":2657,"cf":1109,"rf":300,"la":37.796858,"lo":126.9903113},{"c":"A48283301","s":"백석세아2차-a48283301","q":1,"n":"백석세아2차","sd":"경기도","sg":"양주시","d":"방성리","a":"경기도 양주시 꿈나무로 31-4","h":156,"b":2,"y":1997,"ht":"개별난방","mt":"위탁관리","ma":11861,"lm":"2026-05","tf":2421,"cf":1434,"rf":317,"la":37.8030212,"lo":126.9994665},{"c":"A48283514","s":"백석한승아파트-a48283514","q":1,"n":"백석한승아파트","sd":"경기도","sg":"양주시","d":"오산리","a":"경기도 양주시 권율로 1455-15","h":499,"b":6,"y":2001,"ht":"개별난방","mt":"자치관리","ma":56025,"lm":"2026-05","tf":1858,"cf":909,"rf":236,"la":37.8103513,"lo":126.9788687},{"c":"A48273713","s":"범양마더빌-a48273713","q":1,"n":"범양마더빌","sd":"경기도","sg":"양주시","d":"덕계동","a":"경기도 양주시 평화로 1476-24,경기도 양주시 평화로 1476-20","h":508,"b":7,"y":2006,"ht":"개별난방","mt":"위탁관리","ma":55398,"lm":"2026-05","tf":2062,"cf":1006,"rf":200,"la":37.8214059,"lo":127.0496139},{"c":"A48272104","s":"산내들마을우미린아파트-a48272104","q":0,"n":"산내들마을우미린아파트","sd":"경기도","sg":"양주시","d":"고읍동","a":"경기도 양주시 고읍로35번길 8","h":513,"b":11,"y":2009,"ht":"지역난방","mt":"위탁관리","ma":57766,"lm":"2026-04","tf":2841,"cf":1103,"rf":175,"la":37.7983971,"lo":127.0792845},{"c":"A48272106","s":"산내들마을한양수자인1블럭아파트-a48272106","q":1,"n":"산내들마을한양수자인1블럭아파트","sd":"경기도","sg":"양주시","d":"고읍동","a":"경기도 양주시 고읍로 11-7","h":598,"b":11,"y":2009,"ht":"지역난방","mt":"위탁관리","ma":74295,"lm":"2026-05","tf":2204,"cf":882,"rf":204,"la":37.8025886,"lo":127.0805823},{"c":"A48272107","s":"산내들마을휴먼시아-4단지-a48272107","q":1,"n":"산내들마을휴먼시아(4단지)","sd":"경기도","sg":"양주시","d":"고읍동","a":"경기도 양주시 고읍로 64","h":330,"b":5,"y":2010,"ht":"지역난방","mt":"위탁관리","ma":30555,"lm":"2026-05","tf":2081,"cf":1361,"rf":0,"la":37.7968493,"lo":127.0783769},{"c":"A48283108","s":"샘터마을태영-a48283108","q":1,"n":"샘터마을태영","sd":"경기도","sg":"양주시","d":"복지리","a":"경기도 양주시 호명로 87","h":298,"b":4,"y":1999,"ht":"개별난방","mt":"위탁관리","ma":28456,"lm":"2026-05","tf":2028,"cf":1065,"rf":280,"la":37.7853529,"lo":126.9921063},{"c":"A48283112","s":"서광아침의빛아파트-a48283112","q":1,"n":"서광아침의빛아파트","sd":"경기도","sg":"양주시","d":"가업리","a":"경기도 양주시 양주산성로 838-71","h":492,"b":9,"y":2008,"ht":"개별난방","mt":"위탁관리","ma":51399,"lm":"2026-05","tf":1754,"cf":867,"rf":136,"la":37.7947979,"lo":126.9690625},{"c":"A48273410","s":"성우아파트아침의미소-a48273410","q":1,"n":"성우아파트아침의미소","sd":"경기도","sg":"양주시","d":"삼숭동","a":"경기도 양주시 부흥로 2152-11","h":917,"b":11,"y":2004,"ht":"개별난방","mt":"위탁관리","ma":78203,"lm":"2026-05","tf":2209,"cf":938,"rf":530,"la":37.8050342,"lo":127.0931639},{"c":"A48283116","s":"세아청솔-a48283116","q":1,"n":"세아청솔","sd":"경기도","sg":"양주시","d":"가업리","a":"경기도 양주시 꿈나무로 298","h":619,"b":5,"y":2001,"ht":"개별난방","mt":"위탁관리","ma":48291,"lm":"2026-05","tf":2178,"cf":1065,"rf":380,"la":37.7846785,"lo":126.9822026},{"c":"A48213001","s":"세창리베하우스-a48213001","q":1,"n":"세창리베하우스","sd":"경기도","sg":"양주시","d":"옥정동","a":"경기도 양주시 새터로 37","h":998,"b":18,"y":2003,"ht":"개별난방","mt":"위탁관리","ma":105363,"lm":"2026-05","tf":1879,"cf":810,"rf":251,"la":37.8297529,"lo":127.0863475},{"c":"A10023381","s":"송추역북한산경남아너스빌-a10023381","q":1,"n":"송추역북한산경남아너스빌","sd":"경기도","sg":"양주시","d":"부곡리","a":"경기도 양주시 호국로597번길 15","h":604,"b":8,"y":2022,"ht":"개별난방","mt":"위탁관리","ma":53620,"lm":"2026-05","tf":2252,"cf":1225,"rf":160,"la":37.7198784,"lo":126.9781152},{"c":"A10022167","s":"송추우리마을아파트-a10022167","q":1,"n":"송추우리마을아파트","sd":"경기도","sg":"양주시","d":"부곡리","a":"경기도 양주시 장흥면 부곡리 632-6 송추우리마을아파트","h":140,"b":2,"y":2011,"ht":"개별난방","mt":"위탁관리","ma":10583,"lm":"2026-05","tf":2662,"cf":1467,"rf":442,"la":37.7135173,"lo":126.9671812},{"c":"A48272201","s":"신도브래뉴8차-a48272201","q":1,"n":"신도브래뉴8차","sd":"경기도","sg":"양주시","d":"광사동","a":"경기도 양주시 부흥로 1901","h":400,"b":7,"y":1999,"ht":"개별난방","mt":"위탁관리","ma":39098,"lm":"2026-05","tf":2095,"cf":888,"rf":367,"la":37.7932119,"lo":127.0743246},{"c":"A10022420","s":"신양주모아엘가니케-아파트-a10022420","q":1,"n":"신양주모아엘가니케 아파트","sd":"경기도","sg":"양주시","d":"홍죽리","a":"경기도 양주시 백석읍 홍죽리 964- 신양주모아엘가니케 아파트","h":570,"b":7,"y":2024,"ht":"개별난방","mt":"위탁관리","ma":76765,"lm":"2026-05","tf":1537,"cf":839,"rf":73,"la":37.8025058,"lo":126.967619},{"c":"A48202002","s":"양주-고읍-현대-a48202002","q":1,"n":"양주 고읍 현대","sd":"경기도","sg":"양주시","d":"고읍동","a":"경기도 양주시 고덕로 340-12","h":293,"b":4,"y":1999,"ht":"개별난방","mt":"위탁관리","ma":37077,"lm":"2026-05","tf":2098,"cf":988,"rf":404,"la":37.8016958,"lo":127.0777215},{"c":"A10026955","s":"양주-벨라시티아파트-a10026955","q":1,"n":"양주 벨라시티아파트","sd":"경기도","sg":"양주시","d":"가납리","a":"경기도 양주시 지섬로198번길 16","h":499,"b":6,"y":2017,"ht":"개별난방","mt":"위탁관리","ma":45385,"lm":"2026-05","tf":1994,"cf":1018,"rf":75,"la":37.8199156,"lo":126.9806565},{"c":"A10025028","s":"양주-옥정-세영리첼레이크파크-a10025028","q":1,"n":"양주 옥정 세영리첼레이크파크","sd":"경기도","sg":"양주시","d":"옥정동","a":"경기도 양주시 회천남로 14","h":811,"b":11,"y":2020,"ht":"지역난방","mt":"위탁관리","ma":85269,"lm":"2026-05","tf":2029,"cf":850,"rf":0,"la":37.8191547,"lo":127.1003019},{"c":"A48283901","s":"양주-율정마을-13단지-a48283901","q":1,"n":"양주 율정마을 13단지","sd":"경기도","sg":"양주시","d":"옥정동","a":"경기도 양주시 옥정동로 162","h":962,"b":10,"y":2014,"ht":"지역난방","mt":"위탁관리","ma":143531,"lm":"2026-05","tf":1791,"cf":655,"rf":250,"la":37.8214298,"lo":127.1013658},{"c":"A48284401","s":"양주가납주공아파트-a48284401","q":1,"n":"양주가납주공아파트","sd":"경기도","sg":"양주시","d":"석우리","a":"경기도 양주시 삼일로65번길 156","h":390,"b":7,"y":2006,"ht":"개별난방","mt":"위탁관리","ma":29581,"lm":"2026-05","tf":1820,"cf":1350,"rf":0,"la":37.8287081,"lo":126.9825204},{"c":"A48283107","s":"양주가야2차아파트-a48283107","q":1,"n":"양주가야2차아파트","sd":"경기도","sg":"양주시","d":"복지리","a":"경기도 양주시 호명로 77","h":289,"b":3,"y":1997,"ht":"개별난방","mt":"위탁관리","ma":22340,"lm":"2026-05","tf":2401,"cf":1408,"rf":200,"la":37.7862195,"lo":126.9925148},{"c":"A10024838","s":"양주고읍-lh-13단지-아파트-a10024838","q":1,"n":"양주고읍 LH 13단지 아파트","sd":"경기도","sg":"양주시","d":"광사동","a":"경기도 양주시 고읍남로 94","h":508,"b":4,"y":2020,"ht":"지역난방","mt":"위탁관리","ma":28933,"lm":"2026-05","tf":2094,"cf":1411,"rf":0,"la":37.7883063,"lo":127.0771116},{"c":"A48208006","s":"양주고읍휴먼시아5단지-a48208006","q":1,"n":"양주고읍휴먼시아5단지","sd":"경기도","sg":"양주시","d":"만송동","a":"경기도 양주시 고읍북로 15","h":531,"b":7,"y":2010,"ht":"지역난방","mt":"위탁관리","ma":47962,"lm":"2026-05","tf":1935,"cf":1161,"rf":0,"la":37.7977273,"lo":127.081674},{"c":"A48208003","s":"양주고읍휴먼시아8단지-a48208003","q":1,"n":"양주고읍휴먼시아8단지","sd":"경기도","sg":"양주시","d":"만송동","a":"경기도 양주시 고읍북로 120","h":1124,"b":11,"y":2010,"ht":"지역난방","mt":"위탁관리","ma":92475,"lm":"2026-05","tf":1743,"cf":971,"rf":0,"la":37.7940781,"lo":127.0855588},{"c":"A10023262","s":"양주고읍lh14-a10023262","q":1,"n":"양주고읍LH14","sd":"경기도","sg":"양주시","d":"광사동","a":"경기도 양주시 고읍남로 80","h":372,"b":4,"y":2023,"ht":"지역난방","mt":"위탁관리","ma":26736,"lm":"2026-05","tf":1991,"cf":1409,"rf":0,"la":37.7898711,"lo":127.0768298},{"c":"A48205011","s":"양주금광1차아파트-a48205011","q":0,"n":"양주금광1차아파트","sd":"경기도","sg":"양주시","d":"덕계동","a":"경기도 양주시 평화로1429번길 89-94","h":498,"b":7,"y":2002,"ht":"개별난방","mt":"위탁관리","ma":39529,"lm":"2026-04","tf":2445,"cf":1202,"rf":400,"la":37.8215291,"lo":127.0398367},{"c":"A48205007","s":"양주금광2차포란재아파트-a48205007","q":1,"n":"양주금광2차포란재아파트","sd":"경기도","sg":"양주시","d":"덕계동","a":"경기도 양주시 평화로1438번길 11-12","h":408,"b":4,"y":2002,"ht":"개별난방","mt":"위탁관리","ma":45232,"lm":"2026-05","tf":2296,"cf":1086,"rf":351,"la":37.8190157,"lo":127.0484949},{"c":"A48273302","s":"양주나래-a48273302","q":0,"n":"양주나래","sd":"경기도","sg":"양주시","d":"삼숭동","a":"경기도 양주시 부흥로 2162","h":492,"b":9,"y":1999,"ht":"개별난방","mt":"위탁관리","ma":49230,"lm":"2026-04","tf":2114,"cf":1016,"rf":349,"la":37.8059061,"lo":127.0954988},{"c":"A48270410","s":"양주덕계신우-a48270410","q":0,"n":"양주덕계신우","sd":"경기도","sg":"양주시","d":"덕계동","a":"경기도 양주시 평화로1416번길 14","h":491,"b":3,"y":1994,"ht":"개별난방","mt":"자치관리","ma":45159,"lm":"2026-04","tf":1873,"cf":845,"rf":230,"la":37.8166554,"lo":127.0472567},{"c":"A48270805","s":"양주덕정6단지-a48270805","q":1,"n":"양주덕정6단지","sd":"경기도","sg":"양주시","d":"고암동","a":"경기도 양주시 고암길 252-36","h":977,"b":9,"y":2007,"ht":"개별난방","mt":"위탁관리","ma":70052,"lm":"2026-05","tf":1552,"cf":1056,"rf":0,"la":37.8362139,"lo":127.0734579},{"c":"A48270804","s":"양주덕정주공2단지-a48270804","q":1,"n":"양주덕정주공2단지","sd":"경기도","sg":"양주시","d":"고암동","a":"경기도 양주시 고암길 306-40","h":1935,"b":20,"y":2000,"ht":"개별난방","mt":"위탁관리","ma":194745,"lm":"2026-05","tf":1756,"cf":721,"rf":409,"la":37.8363587,"lo":127.0704822},{"c":"A10024647","s":"양주덕정행복아파트-a10024647","q":1,"n":"양주덕정행복아파트","sd":"경기도","sg":"양주시","d":"고암동","a":"경기도 양주시 고암길 251","h":280,"b":2,"y":2020,"ht":"개별난방","mt":"위탁관리","ma":18496,"lm":"2026-05","tf":1881,"cf":1491,"rf":0,"la":37.8341539,"lo":127.0727763},{"c":"A48283115","s":"양주동화2차초록-a48283115","q":1,"n":"양주동화2차초록","sd":"경기도","sg":"양주시","d":"복지리","a":"경기도 양주시 꿈나무로 311","h":572,"b":9,"y":1999,"ht":"개별난방","mt":"위탁관리","ma":64179,"lm":"2026-05","tf":2051,"cf":964,"rf":374,"la":37.7821419,"lo":126.9840064},{"c":"A48293902","s":"양주백석1단지-a48293902","q":1,"n":"양주백석1단지","sd":"경기도","sg":"양주시","d":"방성리","a":"경기도 양주시 고릉말로46번길 12","h":324,"b":5,"y":2010,"ht":"개별난방","mt":"위탁관리","ma":23973,"lm":"2026-05","tf":2062,"cf":1548,"rf":0,"la":37.8015117,"lo":127.0002129},{"c":"A48079902","s":"양주서희스타힐스1단지-a48079902","q":1,"n":"양주서희스타힐스1단지","sd":"경기도","sg":"양주시","d":"덕정동","a":"경기도 양주시 화합로1325번길 22-31","h":207,"b":4,"y":2014,"ht":"개별난방","mt":"위탁관리","ma":22213,"lm":"2026-05","tf":2367,"cf":1210,"rf":250,"la":37.8481365,"lo":127.0622457},{"c":"A48079903","s":"양주서희스타힐스2단지-a48079903","q":1,"n":"양주서희스타힐스2단지","sd":"경기도","sg":"양주시","d":"덕정동","a":"경기도 양주시 화합로1325번길 22-33","h":821,"b":11,"y":2014,"ht":"개별난방","mt":"위탁관리","ma":83991,"lm":"2026-05","tf":2145,"cf":980,"rf":258,"la":37.8486402,"lo":127.0644744},{"c":"A48294203","s":"양주성우헤스티아-a48294203","q":1,"n":"양주성우헤스티아","sd":"경기도","sg":"양주시","d":"가납리","a":"경기도 양주시 가래비11길 30","h":444,"b":8,"y":2004,"ht":"개별난방","mt":"위탁관리","ma":35667,"lm":"2026-05","tf":2706,"cf":1276,"rf":546,"la":37.8254435,"lo":126.9822433},{"c":"A48281201","s":"양주송추푸른마을-a48281201","q":1,"n":"양주송추푸른마을","sd":"경기도","sg":"양주시","d":"부곡리","a":"경기도 양주시 가마골로 9","h":241,"b":3,"y":1999,"ht":"개별난방","mt":"위탁관리","ma":29147,"lm":"2026-05","tf":2369,"cf":1166,"rf":454,"la":37.719167,"lo":126.9736707},{"c":"A10026075","s":"양주옥정-리젠시빌란트-a10026075","q":1,"n":"양주옥정 리젠시빌란트","sd":"경기도","sg":"양주시","d":"옥정동","a":"경기도 양주시 옥정동로9길 74","h":514,"b":9,"y":2018,"ht":"지역난방","mt":"위탁관리","ma":40775,"lm":"2026-05","tf":2855,"cf":1381,"rf":232,"la":37.8309333,"lo":127.0945939},{"c":"A10024385","s":"양주옥정-모아미래도파크뷰-a10024385","q":1,"n":"양주옥정 모아미래도파크뷰","sd":"경기도","sg":"양주시","d":"옥정동","a":"경기도 양주시 옥정동로9길 106","h":608,"b":7,"y":2021,"ht":"지역난방","mt":"위탁관리","ma":48333,"lm":"2026-05","tf":2685,"cf":1279,"rf":0,"la":37.8296025,"lo":127.0945986},{"c":"A10023160","s":"양주옥정-엘리프아파트-a10023160","q":1,"n":"양주옥정 엘리프아파트","sd":"경기도","sg":"양주시","d":"옥정동","a":"경기도 양주시 옥정서로 210","h":1409,"b":12,"y":2023,"ht":"지역난방","mt":"위탁관리","ma":167171,"lm":"2026-05","tf":1653,"cf":684,"rf":150,"la":37.8326107,"lo":127.0900723},{"c":"A10022534","s":"양주옥정-파티오포레-2단지-a10022534","q":1,"n":"양주옥정 파티오포레 2단지","sd":"경기도","sg":"양주시","d":"옥정동","a":"경기도 양주시 옥정동 905-1 양주옥정 파티오포레 2단지","h":186,"b":16,"y":2024,"ht":"지역난방","mt":"위탁관리","ma":18340,"lm":"2026-05","tf":2663,"cf":1556,"rf":210,"la":37.8246396,"lo":127.0802812},{"c":"A10022544","s":"양주옥정-파티오포레3단지-a10022544","q":1,"n":"양주옥정 파티오포레3단지","sd":"경기도","sg":"양주시","d":"옥정동","a":"경기도 양주시 옥정동 906-2,경기도 양주시 옥정동 906-1 양주옥정 파티오포레3단지","h":160,"b":17,"y":2024,"ht":"지역난방","mt":"위탁관리","ma":15794,"lm":"2026-05","tf":2746,"cf":1519,"rf":210,"la":37.82357,"lo":127.0826605},{"c":"A10024956","s":"양주옥정계룡더파크포레아파트-a10024956","q":1,"n":"양주옥정계룡더파크포레아파트","sd":"경기도","sg":"양주시","d":"옥정동","a":"경기도 양주시 옥정로2길 265","h":901,"b":10,"y":2020,"ht":"지역난방","mt":"위탁관리","ma":121137,"lm":"2026-05","tf":1396,"cf":655,"rf":0,"la":37.8123004,"lo":127.1009455},{"c":"A10023378","s":"양주옥정더원파크빌리지-a10023378","q":1,"n":"양주옥정더원파크빌리지","sd":"경기도","sg":"양주시","d":"옥정동","a":"경기도 양주시 독바위로287번길 51","h":930,"b":28,"y":2023,"ht":"지역난방","mt":"위탁관리","ma":108422,"lm":"2026-05","tf":2572,"cf":1210,"rf":164,"la":37.8222165,"lo":127.0737091},{"c":"A10022741","s":"양주옥정린파밀리에아파트-a10022741","q":1,"n":"양주옥정린파밀리에아파트","sd":"경기도","sg":"양주시","d":"옥정동","a":"경기도 양주시 옥정서로5길 60","h":2049,"b":24,"y":2024,"ht":"지역난방","mt":"위탁관리","ma":215478,"lm":"2026-05","tf":2135,"cf":742,"rf":178,"la":37.8367532,"lo":127.0846961},{"c":"A10023265","s":"양주옥정신도시-한신-더휴-a10023265","q":1,"n":"양주옥정신도시 한신 더휴","sd":"경기도","sg":"양주시","d":"옥정동","a":"경기도 양주시 옥정서로1길 65","h":767,"b":9,"y":2023,"ht":"지역난방","mt":"위탁관리","ma":88459,"lm":"2026-05","tf":2351,"cf":911,"rf":125,"la":37.8133505,"lo":127.086133},{"c":"A10024462","s":"양주옥정신도시1차대방노블랜드더시그니처-a10024462","q":1,"n":"양주옥정신도시1차대방노블랜드더시그니처","sd":"경기도","sg":"양주시","d":"옥정동","a":"경기도 양주시 회천남로 54","h":1483,"b":13,"y":2021,"ht":"지역난방","mt":"위탁관리","ma":169870,"lm":"2026-05","tf":2655,"cf":961,"rf":232,"la":37.8196921,"lo":127.0962423},{"c":"A10024948","s":"양주옥정태영더파크포레아파트-a10024948","q":1,"n":"양주옥정태영더파크포레아파트","sd":"경기도","sg":"양주시","d":"옥정동","a":"경기도 양주시 옥정동로4길 30","h":619,"b":9,"y":2020,"ht":"지역난방","mt":"위탁관리","ma":99824,"lm":"2026-05","tf":1421,"cf":648,"rf":0,"la":37.8133179,"lo":127.099414},{"c":"A10020228","s":"양주옥정파티오포레-1-4-6단지-a10020228","q":0,"n":"양주옥정파티오포레 1,4,6단지","sd":"경기도","sg":"양주시","d":"옥정동","a":"경기도 양주시 옥정동 904-1 양주옥정파티오포레 1,4,6단지","h":307,"b":36,"y":2024,"ht":"지역난방","mt":"위탁관리","ma":0,"lm":"","tf":0,"cf":0,"rf":0,"la":37.8240333,"lo":127.0804582},{"c":"A10022654","s":"양주옥정a-25bl-아파트-a10022654","q":1,"n":"양주옥정A-25BL 아파트","sd":"경기도","sg":"양주시","d":"옥정동","a":"경기도 양주시 회천로 200","h":1215,"b":8,"y":2024,"ht":"지역난방","mt":"위탁관리","ma":78115,"lm":"2026-05","tf":1685,"cf":967,"rf":0,"la":37.8273335,"lo":127.0797566},{"c":"A48272105","s":"양주우남퍼스트빌-a48272105","q":1,"n":"양주우남퍼스트빌","sd":"경기도","sg":"양주시","d":"고읍동","a":"경기도 양주시 고읍로 36-10","h":376,"b":8,"y":2009,"ht":"지역난방","mt":"위탁관리","ma":42223,"lm":"2026-05","tf":3000,"cf":1274,"rf":270,"la":37.8008102,"lo":127.0773891},{"c":"A48272508","s":"양주자이1단지-a48272508","q":1,"n":"양주자이1단지","sd":"경기도","sg":"양주시","d":"삼숭동","a":"경기도 양주시 삼숭로38번길 78-30","h":786,"b":14,"y":2005,"ht":"개별난방","mt":"위탁관리","ma":75786,"lm":"2026-05","tf":2337,"cf":1015,"rf":550,"la":37.794817,"lo":127.1058096},{"c":"A48272604","s":"양주자이2단지-a48272604","q":1,"n":"양주자이2단지","sd":"경기도","sg":"양주시","d":"삼숭동","a":"경기도 양주시 삼숭로38번길 78-12","h":574,"b":9,"y":2005,"ht":"개별난방","mt":"위탁관리","ma":54335,"lm":"2026-05","tf":2222,"cf":1086,"rf":320,"la":37.7956015,"lo":127.103298},{"c":"A48272707","s":"양주자이3단지-a48272707","q":1,"n":"양주자이3단지","sd":"경기도","sg":"양주시","d":"삼숭동","a":"경기도 양주시 삼숭로38번길 55","h":742,"b":10,"y":2005,"ht":"개별난방","mt":"위탁관리","ma":78808,"lm":"2026-05","tf":2135,"cf":1030,"rf":290,"la":37.7978614,"lo":127.1048665},{"c":"A48272809","s":"양주자이4단지-a48272809","q":1,"n":"양주자이4단지","sd":"경기도","sg":"양주시","d":"삼숭동","a":"경기도 양주시 삼숭로38번길 91","h":852,"b":12,"y":2005,"ht":"개별난방","mt":"위탁관리","ma":80698,"lm":"2026-05","tf":2846,"cf":1018,"rf":350,"la":37.7978019,"lo":127.1068999},{"c":"A48272905","s":"양주자이5단지-a48272905","q":1,"n":"양주자이5단지","sd":"경기도","sg":"양주시","d":"삼숭동","a":"경기도 양주시 삼숭로38번길 190","h":652,"b":9,"y":2005,"ht":"개별난방","mt":"위탁관리","ma":67450,"lm":"2026-05","tf":2113,"cf":989,"rf":338,"la":37.79917,"lo":127.1085555},{"c":"A48211006","s":"양주자이6단지-a48211006","q":1,"n":"양주자이6단지","sd":"경기도","sg":"양주시","d":"삼숭동","a":"경기도 양주시 삼숭로58번길 115","h":735,"b":10,"y":2006,"ht":"개별난방","mt":"위탁관리","ma":76869,"lm":"2026-05","tf":2090,"cf":999,"rf":291,"la":37.8025708,"lo":127.1043695},{"c":"A48273103","s":"양주자이7단지-a48273103","q":1,"n":"양주자이7단지","sd":"경기도","sg":"양주시","d":"삼숭동","a":"경기도 양주시 삼숭로58번길 141","h":561,"b":8,"y":2006,"ht":"개별난방","mt":"위탁관리","ma":65507,"lm":"2026-05","tf":1950,"cf":932,"rf":257,"la":37.80395,"lo":127.1046911},{"c":"A48271912","s":"양주푸르지오-a48271912","q":1,"n":"양주푸르지오","sd":"경기도","sg":"양주시","d":"덕계동","a":"경기도 양주시 고덕로 89","h":498,"b":8,"y":2006,"ht":"개별난방","mt":"위탁관리","ma":57208,"lm":"2026-05","tf":2678,"cf":926,"rf":300,"la":37.8127839,"lo":127.0569811},{"c":"A48281202","s":"양주푸른옥마을-a48281202","q":1,"n":"양주푸른옥마을","sd":"경기도","sg":"양주시","d":"일영리","a":"경기도 양주시 권율로 51,경기도 양주시 권율로 53-1","h":262,"b":7,"y":2001,"ht":"개별난방","mt":"위탁관리","ma":27463,"lm":"2026-05","tf":2490,"cf":1283,"rf":370,"la":37.7213121,"lo":126.9451973},{"c":"A48272401","s":"양주한승-a48272401","q":1,"n":"양주한승","sd":"경기도","sg":"양주시","d":"산북동","a":"경기도 양주시 고덕로 108-59","h":498,"b":5,"y":2001,"ht":"개별난방","mt":"위탁관리","ma":56068,"lm":"2026-05","tf":1816,"cf":859,"rf":257,"la":37.8087575,"lo":127.051957},{"c":"A48270606","s":"양주현대아파트-a48270606","q":1,"n":"양주현대아파트","sd":"경기도","sg":"양주시","d":"덕계동","a":"경기도 양주시 회천남로416번길 15","h":350,"b":2,"y":1997,"ht":"개별난방","mt":"위탁관리","ma":28859,"lm":"2026-05","tf":2714,"cf":1413,"rf":462,"la":37.8209304,"lo":127.0569459},{"c":"A48205009","s":"양주현진에버빌1단지-a48205009","q":1,"n":"양주현진에버빌1단지","sd":"경기도","sg":"양주시","d":"덕계동","a":"경기도 양주시 고덕로 160","h":418,"b":8,"y":2007,"ht":"개별난방","mt":"위탁관리","ma":51782,"lm":"2026-05","tf":1989,"cf":1050,"rf":183,"la":37.8064888,"lo":127.0593925},{"c":"A10022665","s":"양주회천-10단지-a10022665","q":1,"n":"양주회천 10단지","sd":"경기도","sg":"양주시","d":"회정동","a":"경기도 양주시 회천로 377","h":680,"b":3,"y":2024,"ht":"지역난방","mt":"위탁관리","ma":40936,"lm":"2026-05","tf":1930,"cf":1248,"rf":0,"la":37.8297205,"lo":127.0615231},{"c":"A10023477","s":"양주회천-한양수자인-17단지-a10023477","q":1,"n":"양주회천 한양수자인(17단지)","sd":"경기도","sg":"양주시","d":"덕계동","a":"경기도 양주시 덕계로 100","h":760,"b":10,"y":2022,"ht":"지역난방","mt":"위탁관리","ma":97600,"lm":"2026-05","tf":1753,"cf":744,"rf":96,"la":37.8182785,"lo":127.0584758},{"c":"A10023328","s":"양주회천14단지주거행복지원센터-a10023328","q":1,"n":"양주회천14단지주거행복지원센터","sd":"경기도","sg":"양주시","d":"덕계동","a":"경기도 양주시 회천남로 486","h":957,"b":7,"y":2023,"ht":"지역난방","mt":"위탁관리","ma":71550,"lm":"2026-05","tf":1566,"cf":935,"rf":0,"la":37.8230208,"lo":127.053817},{"c":"A10022729","s":"양주회천lh15단지-a10022729","q":1,"n":"양주회천LH15단지","sd":"경기도","sg":"양주시","d":"덕계동","a":"경기도 양주시 회천중앙로 282","h":880,"b":5,"y":2024,"ht":"지역난방","mt":"위탁관리","ma":54743,"lm":"2026-05","tf":1798,"cf":1053,"rf":0,"la":37.8234184,"lo":127.0563874},{"c":"A48272103","s":"양주ts푸른솔1차-a48272103","q":1,"n":"양주TS푸른솔1차","sd":"경기도","sg":"양주시","d":"고읍동","a":"경기도 양주시 부흥로 2021-7","h":494,"b":6,"y":1999,"ht":"개별난방","mt":"위탁관리","ma":41129,"lm":"2026-05","tf":2481,"cf":1230,"rf":392,"la":37.8010009,"lo":127.0806424},{"c":"A48211001","s":"양주ts푸른솔3차-a48211001","q":1,"n":"양주TS푸른솔3차","sd":"경기도","sg":"양주시","d":"삼숭동","a":"경기도 양주시 부흥로 2096","h":387,"b":5,"y":2001,"ht":"개별난방","mt":"위탁관리","ma":39531,"lm":"2026-05","tf":2112,"cf":965,"rf":409,"la":37.8049268,"lo":127.0875565},{"c":"A10020747","s":"엘리프옥정시그니처-a10020747","q":1,"n":"엘리프옥정시그니처","sd":"경기도","sg":"양주시","d":"옥정동","a":"경기도 양주시 옥정동 1022- 엘리프옥정시그니처","h":921,"b":9,"y":2025,"ht":"지역난방","mt":"위탁관리","ma":119821,"lm":"2026-05","tf":1660,"cf":810,"rf":0,"la":37.833342,"lo":127.0969444},{"c":"A10023212","s":"옥정-디에트르-에듀포레-아파트-a10023212","q":1,"n":"옥정 디에트르 에듀포레 아파트","sd":"경기도","sg":"양주시","d":"옥정동","a":"경기도 양주시 옥정서로5길 55","h":1086,"b":8,"y":2023,"ht":"지역난방","mt":"위탁관리","ma":116001,"lm":"2026-05","tf":2491,"cf":1008,"rf":98,"la":37.8338992,"lo":127.0848803},{"c":"A10027239","s":"옥정-센트럴파크-푸르지오-아파트-a10027239","q":1,"n":"옥정 센트럴파크 푸르지오 아파트","sd":"경기도","sg":"양주시","d":"옥정동","a":"경기도 양주시 옥정서로 130","h":1862,"b":18,"y":2016,"ht":"지역난방","mt":"위탁관리","ma":149525,"lm":"2026-05","tf":2850,"cf":1136,"rf":250,"la":37.8244773,"lo":127.0890948},{"c":"A10023794","s":"옥정-중흥s-클래스센텀시티1bl-a10023794","q":1,"n":"옥정 중흥S-클래스센텀시티1BL","sd":"경기도","sg":"양주시","d":"옥정동","a":"경기도 양주시 옥정서로 72","h":849,"b":11,"y":2022,"ht":"지역난방","mt":"위탁관리","ma":91886,"lm":"2026-05","tf":2454,"cf":938,"rf":152,"la":37.8196464,"lo":127.0880406},{"c":"A10023675","s":"옥정역-로제비앙-메트로파크-1단지-a10023675","q":1,"n":"옥정역 로제비앙 메트로파크 1단지","sd":"경기도","sg":"양주시","d":"삼숭동","a":"경기도 양주시 부흥로 2128","h":946,"b":11,"y":2022,"ht":"개별난방","mt":"위탁관리","ma":80492,"lm":"2026-05","tf":2587,"cf":1206,"rf":198,"la":37.8056602,"lo":127.0921097},{"c":"A10023674","s":"옥정역-로제비앙-메트로파크-2단지-a10023674","q":1,"n":"옥정역 로제비앙 메트로파크 2단지","sd":"경기도","sg":"양주시","d":"삼숭동","a":"경기도 양주시 부흥로 2126","h":297,"b":5,"y":2022,"ht":"개별난방","mt":"위탁관리","ma":34378,"lm":"2026-05","tf":2245,"cf":1187,"rf":91,"la":37.8055534,"lo":127.0923004},{"c":"A10023408","s":"옥정유림노르웨이숲아파트-a10023408","q":1,"n":"옥정유림노르웨이숲아파트","sd":"경기도","sg":"양주시","d":"옥정동","a":"경기도 양주시 옥정로2길 229","h":1140,"b":14,"y":2023,"ht":"개별난방+기타","mt":"위탁관리","ma":125553,"lm":"2026-05","tf":2558,"cf":966,"rf":209,"la":37.8127718,"lo":127.0969152},{"c":"A10023789","s":"옥정중앙역s-클래스센텀시티3블럭-a10023789","q":1,"n":"옥정중앙역S-클래스센텀시티3블럭","sd":"경기도","sg":"양주시","d":"옥정동","a":"경기도 양주시 회천남로 116","h":666,"b":8,"y":2022,"ht":"지역난방","mt":"위탁관리","ma":71113,"lm":"2026-05","tf":2564,"cf":1029,"rf":234,"la":37.8196128,"lo":127.0901236},{"c":"A48291203","s":"우남송추마을아파트-a48291203","q":1,"n":"우남송추마을아파트","sd":"경기도","sg":"양주시","d":"부곡리","a":"경기도 양주시 가마골로 40-8","h":395,"b":5,"y":2001,"ht":"개별난방","mt":"위탁관리","ma":41787,"lm":"2026-05","tf":2237,"cf":1022,"rf":500,"la":37.7217807,"lo":126.9772896},{"c":"A48272301","s":"유승한내들9단지-a48272301","q":1,"n":"유승한내들9단지","sd":"경기도","sg":"양주시","d":"광사동","a":"경기도 양주시 고읍로 118-16","h":470,"b":8,"y":2009,"ht":"지역난방","mt":"위탁관리","ma":51405,"lm":"2026-05","tf":2560,"cf":1081,"rf":220,"la":37.7945521,"lo":127.0819331},{"c":"A48205005","s":"윤중-a48205005","q":0,"n":"윤중","sd":"경기도","sg":"양주시","d":"덕계동","a":"경기도 양주시 회천남로416번길 17","h":320,"b":2,"y":2002,"ht":"개별난방","mt":"위탁관리","ma":23008,"lm":"2026-04","tf":2622,"cf":1311,"rf":470,"la":37.8220895,"lo":127.0574609},{"c":"A48283902","s":"율정마을7단지-a48283902","q":1,"n":"율정마을7단지","sd":"경기도","sg":"양주시","d":"옥정동","a":"경기도 양주시 옥정동로 257","h":1256,"b":14,"y":2014,"ht":"지역난방","mt":"위탁관리","ma":105894,"lm":"2026-05","tf":1562,"cf":920,"rf":0,"la":37.8300652,"lo":127.0971864},{"c":"A48270703","s":"은동마을아파트-덕정주공1단지-a48270703","q":1,"n":"은동마을아파트(덕정주공1단지)","sd":"경기도","sg":"양주시","d":"덕정동","a":"경기도 양주시 화합로1426번길 39","h":792,"b":10,"y":2001,"ht":"개별난방","mt":"위탁관리","ma":99801,"lm":"2026-05","tf":1676,"cf":783,"rf":206,"la":37.8392696,"lo":127.0682632},{"c":"A48208002","s":"은빛마을유승한내들-a48208002","q":1,"n":"은빛마을유승한내들","sd":"경기도","sg":"양주시","d":"만송동","a":"경기도 양주시 고읍북로 28-8","h":412,"b":6,"y":2009,"ht":"지역난방","mt":"위탁관리","ma":33728,"lm":"2026-05","tf":3011,"cf":1401,"rf":268,"la":37.7970041,"lo":127.0830659},{"c":"A48208001","s":"은빛마을한양수자인2단지-a48208001","q":0,"n":"은빛마을한양수자인2단지","sd":"경기도","sg":"양주시","d":"만송동","a":"경기도 양주시 고읍로 117-7","h":434,"b":9,"y":2010,"ht":"지역난방","mt":"위탁관리","ma":46510,"lm":"2026-04","tf":3574,"cf":1330,"rf":456,"la":37.795678,"lo":127.082872},{"c":"A10022901","s":"이편한세상덕정역더스카이-a10022901","q":1,"n":"이편한세상덕정역더스카이","sd":"경기도","sg":"양주시","d":"회정동","a":"경기도 양주시 평화로 1723","h":629,"b":5,"y":2023,"ht":"개별난방","mt":"위탁관리","ma":63675,"lm":"2026-05","tf":2259,"cf":1248,"rf":84,"la":37.8427525,"lo":127.0541312},{"c":"A10020748","s":"장흥역-경남아너스빌-북한산뷰5블럭-a10020748","q":1,"n":"장흥역 경남아너스빌 북한산뷰5블럭","sd":"경기도","sg":"양주시","d":"일영리","a":"경기도 양주시 장흥면 일영리 605-,경기도 양주시 장흥면 일영리 143-11 장흥역 경남아너스빌 북한산뷰5블럭","h":283,"b":6,"y":2025,"ht":"개별난방","mt":"위탁관리","ma":31018,"lm":"2026-05","tf":2410,"cf":1284,"rf":190,"la":37.7174028,"lo":126.9383832},{"c":"A10020734","s":"장흥역-경남아너스빌북한산뷰-4블럭-a10020734","q":1,"n":"장흥역 경남아너스빌북한산뷰 4블럭","sd":"경기도","sg":"양주시","d":"일영리","a":"경기도 양주시 장흥면 일영리 85-4 장흥역 경남아너스빌북한산뷰 4블럭","h":458,"b":8,"y":2025,"ht":"개별난방","mt":"위탁관리","ma":50273,"lm":"2026-05","tf":2012,"cf":1036,"rf":200,"la":37.7190976,"lo":126.9389106},{"c":"A10022817","s":"제일풍경채-옥정-a10022817","q":1,"n":"제일풍경채 옥정","sd":"경기도","sg":"양주시","d":"옥정동","a":"경기도 양주시 옥정동로2길 20","h":1304,"b":16,"y":2023,"ht":"지역난방","mt":"위탁관리","ma":200675,"lm":"2026-05","tf":1487,"cf":647,"rf":0,"la":37.8121398,"lo":127.092639},{"c":"A10023236","s":"제일풍경채레이크시티1단지-a10023236","q":1,"n":"제일풍경채레이크시티1단지","sd":"경기도","sg":"양주시","d":"옥정동","a":"경기도 양주시 옥정동로 212","h":1246,"b":13,"y":2023,"ht":"지역난방","mt":"위탁관리","ma":141807,"lm":"2026-05","tf":2387,"cf":939,"rf":110,"la":37.8257847,"lo":127.1006058},{"c":"A10023290","s":"제일풍경채레이크시티2단지-a10023290","q":1,"n":"제일풍경채레이크시티2단지","sd":"경기도","sg":"양주시","d":"옥정동","a":"경기도 양주시 옥정동로 190","h":1228,"b":13,"y":2023,"ht":"지역난방","mt":"위탁관리","ma":139983,"lm":"2026-05","tf":2458,"cf":908,"rf":120,"la":37.8236464,"lo":127.1019709},{"c":"A10021987","s":"한국아파트-a10021987","q":1,"n":"한국아파트","sd":"경기도","sg":"양주시","d":"덕정동","a":"경기도 양주시 덕정동 286-9,경기도 양주시 덕정동 218-1 한국아파트","h":216,"b":4,"y":1989,"ht":"","mt":"자치관리","ma":12576,"lm":"2026-05","tf":964,"cf":462,"rf":172,"la":37.8394095,"lo":127.0637414},{"c":"A48270504","s":"한주아파트-a48270504","q":1,"n":"한주아파트","sd":"경기도","sg":"양주시","d":"덕계동","a":"경기도 양주시 평화로1429번길 66","h":320,"b":2,"y":1999,"ht":"개별난방","mt":"위탁관리","ma":27617,"lm":"2026-05","tf":2114,"cf":1107,"rf":212,"la":37.8207711,"lo":127.044499},{"c":"A48272302","s":"해동마을신도브래뉴-a48272302","q":1,"n":"해동마을신도브래뉴","sd":"경기도","sg":"양주시","d":"광사동","a":"경기도 양주시 고읍남로39번길 48","h":744,"b":14,"y":2009,"ht":"지역난방","mt":"위탁관리","ma":98631,"lm":"2026-05","tf":2380,"cf":836,"rf":212,"la":37.7913991,"lo":127.0784557},{"c":"A48272303","s":"해동마을한양수자인3차-a48272303","q":1,"n":"해동마을한양수자인3차","sd":"경기도","sg":"양주시","d":"광사동","a":"경기도 양주시 고읍남로39번길 84","h":764,"b":14,"y":2010,"ht":"지역난방","mt":"위탁관리","ma":71915,"lm":"2026-05","tf":2765,"cf":1017,"rf":336,"la":37.7888017,"lo":127.0790241},{"c":"A48205008","s":"현진에버빌2단지-a48205008","q":1,"n":"현진에버빌2단지","sd":"경기도","sg":"양주시","d":"덕계동","a":"경기도 양주시 고덕로 159","h":415,"b":7,"y":2007,"ht":"개별난방","mt":"위탁관리","ma":37062,"lm":"2026-05","tf":2939,"cf":1496,"rf":384,"la":37.8069594,"lo":127.060899},{"c":"A48217001","s":"회정금용-a48217001","q":0,"n":"회정금용","sd":"경기도","sg":"양주시","d":"회정동","a":"경기도 양주시 평화로 1552-19,경기도 양주시 평화로 1552-8","h":184,"b":2,"y":1992,"ht":"개별난방","mt":"자치관리","ma":17891,"lm":"2026-04","tf":1561,"cf":913,"rf":300,"la":37.8271565,"lo":127.0537261},{"c":"A48217002","s":"회정범양-a48217002","q":1,"n":"회정범양","sd":"경기도","sg":"양주시","d":"회정동","a":"경기도 양주시 평화로1570번길 36","h":883,"b":12,"y":2003,"ht":"개별난방","mt":"위탁관리","ma":91592,"lm":"2026-05","tf":2082,"cf":838,"rf":422,"la":37.8282212,"lo":127.0553302},{"c":"A10023008","s":"회천-대광로제비앙-더-센트럴-a10023008","q":1,"n":"회천 대광로제비앙 더 센트럴","sd":"경기도","sg":"양주시","d":"덕계동","a":"경기도 양주시 회천중앙로 220","h":526,"b":5,"y":2023,"ht":"지역난방","mt":"위탁관리","ma":43549,"lm":"2026-05","tf":3341,"cf":1395,"rf":129,"la":37.8171602,"lo":127.0526368},{"c":"A10022911","s":"회천베네스트하우스아파트-a10022911","q":1,"n":"회천베네스트하우스아파트","sd":"경기도","sg":"양주시","d":"덕계동","a":"경기도 양주시 회천중앙로 200","h":995,"b":15,"y":2023,"ht":"지역난방","mt":"위탁관리","ma":151434,"lm":"2026-05","tf":1496,"cf":615,"rf":89,"la":37.8149162,"lo":127.0528761},{"c":"A10022547","s":"회천트루엘시그니처-a10022547","q":1,"n":"회천트루엘시그니처","sd":"경기도","sg":"양주시","d":"덕계동","a":"경기도 양주시 덕계동 0 회천트루엘시그니처","h":869,"b":8,"y":2024,"ht":"지역난방","mt":"위탁관리","ma":107900,"lm":"2026-05","tf":1703,"cf":737,"rf":70,"la":37.8116025,"lo":127.0496174},{"c":"A10022798","s":"회천파밀리에더퍼스트-a10022798","q":1,"n":"회천파밀리에더퍼스트","sd":"경기도","sg":"양주시","d":"덕계동","a":"경기도 양주시 덕계로 111","h":1304,"b":16,"y":2024,"ht":"지역난방","mt":"위탁관리","ma":141327,"lm":"2026-05","tf":1991,"cf":771,"rf":60,"la":37.8155707,"lo":127.0590624},{"c":"A48273901","s":"휴먼시아하늘빛마을-a48273901","q":1,"n":"휴먼시아하늘빛마을","sd":"경기도","sg":"양주시","d":"고암동","a":"경기도 양주시 고암길 223","h":608,"b":8,"y":2007,"ht":"개별난방","mt":"위탁관리","ma":50701,"lm":"2026-05","tf":2693,"cf":1217,"rf":426,"la":37.8334964,"lo":127.073554},{"c":"A48284102","s":"희망아파트-a48284102","q":1,"n":"희망아파트","sd":"경기도","sg":"양주시","d":"광석리","a":"경기도 양주시 광적로 85-18,경기도 양주시 광적로 85-16","h":436,"b":4,"y":1996,"ht":"개별난방","mt":"자치관리","ma":33455,"lm":"2026-05","tf":2416,"cf":1112,"rf":500,"la":37.8260637,"lo":126.9793926},{"c":"A10022545","s":"힐스테이트양주옥정파티오포레5단지-a10022545","q":1,"n":"힐스테이트양주옥정파티오포레5단지","sd":"경기도","sg":"양주시","d":"옥정동","a":"경기도 양주시 옥정동 910-1 힐스테이트양주옥정파티오포레5단지","h":156,"b":12,"y":2024,"ht":"지역난방","mt":"위탁관리","ma":15407,"lm":"2026-05","tf":2976,"cf":1558,"rf":210,"la":37.8238812,"lo":127.0848974},{"c":"A10025608","s":"e편한세상-옥정-더퍼스트-아파트-a10025608","q":1,"n":"e편한세상 옥정 더퍼스트 아파트","sd":"경기도","sg":"양주시","d":"옥정동","a":"경기도 양주시 옥정서로1길 60","h":1566,"b":17,"y":2019,"ht":"지역난방","mt":"위탁관리","ma":169030,"lm":"2026-05","tf":2145,"cf":869,"rf":100,"la":37.8156465,"lo":127.085149},{"c":"A10022629","s":"e편한세상-옥정-리더스가든-a10022629","q":1,"n":"e편한세상 옥정 리더스가든","sd":"경기도","sg":"양주시","d":"옥정동","a":"경기도 양주시 회천로 234","h":938,"b":14,"y":2024,"ht":"지역난방","mt":"위탁관리","ma":107766,"lm":"2026-05","tf":2382,"cf":997,"rf":150,"la":37.828753,"lo":127.0775541},{"c":"A10024848","s":"e편한세상-옥정-메트로포레-a10024848","q":1,"n":"e편한세상 옥정 메트로포레","sd":"경기도","sg":"양주시","d":"옥정동","a":"경기도 양주시 옥정동로 10","h":2038,"b":24,"y":2020,"ht":"지역난방","mt":"위탁관리","ma":219495,"lm":"2026-05","tf":2283,"cf":953,"rf":93,"la":37.8114916,"lo":127.0886225},{"c":"A10026259","s":"e편한세상-옥정-에듀써밋-a10026259","q":1,"n":"e편한세상 옥정 에듀써밋","sd":"경기도","sg":"양주시","d":"옥정동","a":"경기도 양주시 옥정동로1길 63","h":1160,"b":13,"y":2018,"ht":"지역난방","mt":"위탁관리","ma":124702,"lm":"2026-05","tf":2528,"cf":1075,"rf":228,"la":37.8164612,"lo":127.0928484},{"c":"A10026829","s":"e편한세상-옥정어반센트럴-a10026829","q":1,"n":"e편한세상 옥정어반센트럴","sd":"경기도","sg":"양주시","d":"옥정동","a":"경기도 양주시 옥정로5길 35","h":761,"b":8,"y":2017,"ht":"지역난방","mt":"위탁관리","ma":81553,"lm":"2026-05","tf":2376,"cf":1075,"rf":135,"la":37.8213704,"lo":127.090121},{"c":"A10025844","s":"gs건설제이드웰nhf-a10025844","q":1,"n":"GS건설제이드웰NHF","sd":"경기도","sg":"양주시","d":"옥정동","a":"경기도 양주시 옥정동로 104","h":947,"b":9,"y":2018,"ht":"지역난방","mt":"위탁관리","ma":144176,"lm":"2026-05","tf":1417,"cf":585,"rf":30,"la":37.8150644,"lo":127.1010822},{"c":"A10026963","s":"lh양주옥정16단지-a10026963","q":1,"n":"LH양주옥정16단지","sd":"경기도","sg":"양주시","d":"옥정동","a":"경기도 양주시 회천남로 115","h":1618,"b":8,"y":2017,"ht":"지역난방","mt":"위탁관리","ma":98457,"lm":"2026-05","tf":1638,"cf":962,"rf":0,"la":37.816963,"lo":127.0892562},{"c":"A10026014","s":"lh양주옥정3-a10026014","q":1,"n":"LH양주옥정3","sd":"경기도","sg":"양주시","d":"옥정동","a":"경기도 양주시 옥정서로 254","h":1500,"b":9,"y":2018,"ht":"지역난방","mt":"위탁관리","ma":86253,"lm":"2026-05","tf":1745,"cf":1135,"rf":0,"la":37.8353877,"lo":127.0889551},{"c":"A10026991","s":"lh옥정8단지아파트-a10026991","q":1,"n":"LH옥정8단지아파트","sd":"경기도","sg":"양주시","d":"옥정동","a":"경기도 양주시 옥정동로 258","h":1550,"b":10,"y":2017,"ht":"지역난방","mt":"위탁관리","ma":98044,"lm":"2026-05","tf":1590,"cf":959,"rf":0,"la":37.8301869,"lo":127.1003866},{"c":"A48272101","s":"ts-푸른솔2차아파트-a48272101","q":1,"n":"TS 푸른솔2차아파트","sd":"경기도","sg":"양주시","d":"고읍동","a":"경기도 양주시 부흥로 2021-12","h":204,"b":3,"y":2000,"ht":"개별난방","mt":"위탁관리","ma":20419,"lm":"2026-05","tf":2278,"cf":1031,"rf":492,"la":37.801935,"lo":127.0816126}]